<resources>

    <!-- Apps feature - App -->
    <string name="app_name">Komi Store</string>

    <string name="navigate_back">العودة</string>
    <string name="check_for_updates">التحقق من التحديثات</string>

    <!-- Apps feature - Errors / messages -->
    <string name="cannot_launch">تعذر تشغيل %1$s</string>
    <string name="failed_to_open">فشل فتح %1$s</string>
    <string name="failed_to_update">فشل تحديث %1$s: %2$s</string>
    <string name="update_all_failed">فشل تحديث الكل: %1$s</string>
    <string name="all_apps_updated_successfully">تم تحديث جميع التطبيقات بنجاح</string>
    <string name="no_updates_available">لا توجد تحديثات متاحة</string>

    <!-- Apps feature - Search -->
    <string name="search_your_apps">ابحث في تطبيقاتك</string>
    <string name="no_apps_found">لم يتم العثور على تطبيقات</string>

    <!-- Apps feature - Actions -->
    <string name="update_all">تحديث الكل</string>
    <string name="update">تحديث</string>
    <string name="open">فتح</string>
    <string name="cancel">إلغاء</string>

    <!-- Apps feature - Update states -->
    <string name="checking">جارٍ التحقق…</string>
    <string name="updated_successfully">تم التحديث بنجاح</string>
    <string name="error_with_message">خطأ: %1$s</string>

    <!-- Apps feature - Update all progress -->
    <string name="updating_x_of_y">جارٍ تحديث %1$d من %2$d</string>
    <string name="currently_updating">الحالي: %1$s</string>


    <!-- Auth general -->
    <string name="waiting_for_authorization">في انتظار التفويض…</string>
    <string name="signed_in">تم تسجيل الدخول!</string>
    <string name="redirecting_message">يمكنك الآن استخدام التطبيق. جارٍ إعادة التوجيه…</string>
    <string name="try_again">حاول مرة أخرى</string>

    <!-- Errors -->
    <string name="auth_error_with_message">خطأ: %1$s</string>

    <!-- Device flow -->
    <string name="enter_code_on_github">أدخل هذا الرمز على GitHub:</string>
    <string name="copy_code">نسخ الرمز</string>
    <string name="open_github">فتح GitHub</string>

    <!-- Logged out -->
    <string name="unlock_full_experience">افتح التجربة\nالكاملة</string>

    <string name="more_requests">المزيد من الطلبات</string>
    <string name="more_requests_description">
        سجّل الدخول للحصول على حدود أعلى لطلبات API وتجنب الانقطاعات.
    </string>

    <string name="sign_in_with_github">تسجيل الدخول بـ GitHub</string>

    <string name="error_unknown">خطأ غير معروف</string>


    <string name="search_repositories_hint">ابحث عن مستودع، وصف…</string>

    <!-- Filters -->
    <string name="filter_by_language">تصفية حسب اللغة</string>

    <!-- Results -->
    <string name="results_found">تم العثور على %1$d نتيجة</string>
    <string name="search_results_hidden_by_seen_filter">جميع النتائج مخفية بسبب فلتر 'إخفاء المُشاهَد'</string>
    <string name="show_all_results">تعطيل فلتر 'إخفاء المُشاهَد'</string>
    <string name="searching_for_unseen_repos">البحث عن مستودعات لم تتم مشاهدتها…</string>


    <!-- Sorting -->
    <string name="sort_by">ترتيب حسب</string>
    <string name="close">إغلاق</string>

    <string name="sort_most_stars">الأكثر نجوماً</string>
    <string name="sort_most_forks">الأكثر تفرعاً</string>
    <string name="sort_best_match">الأفضل تطابقاً</string>
    <string name="sort_recently_released">الأحدث إصداراً</string>

    <string name="sort_order_descending">تنازلي</string>
    <string name="sort_order_ascending">تصاعدي</string>
    <string name="sort_label">ترتيب</string>

    <!-- Programming languages -->
    <string name="language_all">جميع اللغات</string>
    <string name="language_kotlin">Kotlin</string>
    <string name="language_java">Java</string>
    <string name="language_javascript">JavaScript</string>
    <string name="language_typescript">TypeScript</string>
    <string name="language_python">Python</string>
    <string name="language_swift">Swift</string>
    <string name="language_rust">Rust</string>
    <string name="language_go">Go</string>
    <string name="language_csharp">C#</string>
    <string name="language_cpp">C++</string>
    <string name="language_c">C</string>
    <string name="language_dart">Dart</string>
    <string name="language_ruby">Ruby</string>
    <string name="language_php">PHP</string>

    <string name="search_failed">فشل البحث</string>
    <string name="no_repositories_found">لم يتم العثور على مستودعات</string>

    <!-- Profile -->
    <string name="profile_title">الملف الشخصي</string>

    <string name="language_follow_system">اتباع النظام</string>
    <string name="language_restart_required">أعد التشغيل لتطبيق اللغة الجديدة.</string>
    <string name="language_restart_action">إعادة التشغيل</string>

    <!-- Appearance -->
    <string name="theme_color">لون السمة</string>
    <string name="amoled_black_theme">سمة AMOLED السوداء</string>
    <string name="amoled_black_description">خلفية سوداء نقية للوضع الداكن</string>


    <!-- Account -->
    <string name="logout">تسجيل الخروج</string>

    <string name="proxy_host">المضيف</string>
    <string name="proxy_port">المنفذ</string>
    <string name="proxy_username">اسم المستخدم (اختياري)</string>
    <string name="proxy_password">كلمة المرور (اختياري)</string>
    <string name="proxy_save">حفظ الوكيل</string>
    <string name="proxy_saved">تم حفظ إعدادات الوكيل</string>
    <string name="failed_to_save_proxy_settings">فشل حفظ إعدادات الوكيل</string>
    <string name="proxy_host_required">المضيف مطلوب</string>
    <string name="proxy_host_invalid">أدخل اسم مضيف أو عنوان IP صالحًا</string>
    <string name="invalid_proxy_port">منفذ الوكيل غير صالح</string>
    <string name="proxy_test_success">الاتصال ناجح (%1$d مللي ثانية)</string>
    <string name="proxy_test_error_dns">تعذر تحليل المضيف. تحقق من عنوان الوكيل.</string>
    <string name="proxy_test_error_unreachable">تعذر الوصول إلى خادم الوكيل.</string>
    <string name="proxy_test_error_timeout">انتهت مهلة الاتصال.</string>
    <string name="proxy_test_error_auth_required">يلزم التحقق من الوكيل.</string>
    <string name="proxy_test_error_status">استجابة غير متوقعة: HTTP %1$d</string>
    <string name="proxy_test_error_unknown">فشل اختبار الاتصال</string>

    <!-- Snackbar -->
    <string name="logout_success">تم تسجيل الخروج بنجاح، جارٍ إعادة التوجيه...</string>

    <!-- Dialog -->
    <string name="warning">تحذير!</string>
    <string name="logout_confirmation">هل أنت متأكد أنك تريد تسجيل الخروج؟</string>

    <!-- Theme names -->
    <string name="theme_forest">غابة</string>
    <string name="theme_nord">Nord</string>
    <string name="theme_cream">Cream</string>
    <string name="theme_plum">Plum</string>

    <!-- Navigation & actions -->
    <string name="open_repository">فتح المستودع</string>
    <string name="open_in_browser">فتح في المتصفح</string>
    <string name="cancel_download">إلغاء التنزيل</string>
    <string name="show_install_options">عرض خيارات التثبيت</string>

    <string name="retry">إعادة المحاولة</string>
    <string name="no_description">لا يوجد وصف.</string>
    <string name="no_release_notes">لا توجد ملاحظات إصدار.</string>
    <string name="report_issue">الإبلاغ عن مشكلة</string>

    <!-- Headers -->
    <string name="about_this_app">حول هذا التطبيق</string>
    <string name="install_logs">سجلات التثبيت</string>
    <string name="whats_new">ما الجديد</string>

    <!-- Install status -->
    <string name="installed">مثبت</string>
    <string name="update_available">تحديث متاح</string>
    <string name="not_available">غير متاح</string>
    <string name="install_latest">تثبيت الأحدث</string>

    <!-- Download stages -->
    <string name="downloading">جارٍ التنزيل</string>
    <string name="updating">جارٍ التحديث</string>
    <string name="verifying">جارٍ التحقق</string>
    <string name="installing">جارٍ التثبيت</string>
    <string name="pending_install">في انتظار التثبيت</string>

    <!-- Uninstall / Open -->
    <string name="uninstall">إزالة التثبيت</string>
    <string name="open_app">فتح</string>
    <string name="downgrade_requires_uninstall">الرجوع لإصدار أقدم يتطلب إزالة التثبيت</string>
    <string name="downgrade_warning_message">تثبيت الإصدار %1$s يتطلب إزالة الإصدار الحالي (%2$s) أولاً. سيتم فقدان بيانات التطبيق.</string>
    <string name="uninstall_first">إزالة التثبيت أولاً</string>
    <string name="install_version">تثبيت %1$s</string>
    <string name="failed_to_open_app">فشل فتح %1$s</string>
    <string name="failed_to_uninstall">فشل إزالة تثبيت %1$s</string>

    <!-- Install helpers -->
    <string name="open_in_obtainium">فتح في Obtainium</string>
    <string name="obtainium_description">إدارة التحديثات تلقائياً</string>
    <string name="inspect_with_appmanager">فحص بـ AppManager</string>
    <string name="appmanager_description">فحص الأذونات والمتتبعات والأمان</string>

    <!-- Author -->
    <string name="profile">الملف الشخصي</string>

    <!-- Stats -->
    <string name="forks">التفرعات</string>
    <string name="stars">النجوم</string>
    <string name="issues">المشكلات</string>
    <string name="downloads">التنزيلات</string>
    <string name="license">الترخيص</string>
    <string name="license_none">—</string>
    <string name="fetch_more_from_github">جلب المزيد من GitHub</string>
    <string name="fetching_from_github">جارٍ الجلب من GitHub…</string>
    <string name="no_more_github_results">لا توجد نتائج أخرى على GitHub</string>
    <string name="explore_error">فشل الجلب من GitHub. حاول مرة أخرى.</string>

    <string name="architecture_compatible">متوافق مع المعمارية</string>
    <string name="update_to_version">التحديث إلى %1$s</string>

    <string name="installer_saved_downloads">تم حفظ المثبت في مجلد التنزيلات</string>

    <!-- Download / install states -->
    <string name="log_download_started">بدأ التنزيل</string>
    <string name="log_downloaded">تم التنزيل</string>
    <string name="log_update_started">بدأ التحديث</string>
    <string name="log_installed">تم التثبيت</string>
    <string name="log_updated">تم التحديث</string>
    <string name="log_cancelled">تم الإلغاء</string>
    <string name="log_install_started">بدأ التثبيت</string>
    <string name="log_error">خطأ</string>
    <string name="log_error_with_message">خطأ: %1$s</string>

    <!-- External tools -->
    <string name="log_prepare_appmanager">التحضير لـ AppManager</string>
    <string name="log_opened_appmanager">تم الفتح في AppManager</string>
    <string name="log_permission_blocked">تم حظر إذن التثبيت بواسطة سياسة الجهاز</string>
    <string name="log_opened_external_installer">تم الفتح في المثبت الخارجي</string>

    <!-- External installer -->
    <string name="install_permission_unavailable">إذن التثبيت غير متاح</string>
    <string name="install_permission_blocked_message">تم تنزيل ملف APK بنجاح لكن هذا الجهاز لا يسمح بالتثبيت المباشر. هل تريد فتحه بمثبت خارجي؟</string>
    <string name="open_with_external_installer">فتح بمثبت خارجي</string>
    <string name="external_installer_description">استخدم تطبيقاً خارجياً لتثبيت ملف APK</string>

    <!-- Errors -->
    <string name="error_generic">خطأ: %1$s</string>



    <string name="home_finding_repositories">جارٍ البحث عن مستودعات...</string>
    <string name="home_retry">إعادة المحاولة</string>
    <string name="home_failed_to_load_repositories">فشل تحميل المستودعات</string>

    <string name="updated_on_date">تم التحديث في %1$s</string>

    <string name="rate_limit_exceeded">تم تجاوز حد الطلبات</string>
    <string name="rate_limit_used_all">لقد استخدمت جميع طلبات API البالغة %1$d.</string>
    <string name="rate_limit_used_all_free">لقد استخدمت جميع الطلبات المجانية البالغة %1$d.</string>
    <string name="rate_limit_resets_in_minutes">يتم إعادة التعيين خلال %1$d دقيقة</string>
    <string name="rate_limit_tip_sign_in">💡 سجّل الدخول للحصول على 5,000 طلب في الساعة بدلاً من 60!</string>
    <string name="rate_limit_sign_in">تسجيل الدخول</string>
    <string name="rate_limit_ok">حسناً</string>
    <string name="rate_limit_close">إغلاق</string>

    <string name="system_font">خط النظام</string>
    <string name="system_font_description">مطابقة خط جهازك لقراءة أفضل</string>

    <string name="theme_light">فاتح</string>
    <string name="theme_dark">داكن</string>
    <string name="theme_system">النظام</string>

    <string name="added_to_favourites">تمت إضافة المستودع إلى المفضلة</string>
    <string name="removed_from_favourites">تمت إزالة المستودع من المفضلة</string>
    <string name="add_to_favourites">إضافة إلى المفضلة</string>
    <string name="remove_from_favourites">إزالة من المفضلة</string>
    <string name="favourites">المفضلة</string>

    <string name="added_just_now">أُضيف للتو</string>
    <string name="added_hours_ago">أُضيف منذ %1$d ساعة</string>
    <string name="added_yesterday">أُضيف أمس</string>
    <string name="added_days_ago">أُضيف منذ %1$d يوم</string>
    <string name="added_on_date">أُضيف في %1$s</string>

    <string name="starred_repositories">المستودعات المميزة بنجمة</string>
    <string name="repository_starred">المستودع مميز بنجمة</string>
    <string name="repository_not_starred">المستودع غير مميز بنجمة</string>
    <string name="star_from_github">يمكنك تمييز مستودع بنجمة من GitHub</string>
    <string name="unstar_from_github">يمكنك إزالة النجمة عن مستودع من GitHub</string>

    <string name="sign_in_required">تسجيل الدخول مطلوب</string>
    <string name="sign_in_with_github_for_stars">سجّل الدخول بـ GitHub لرؤية مستودعاتك المميزة بنجمة</string>
    <string name="no_starred_repos">لا توجد مستودعات مميزة بنجمة</string>
    <string name="star_repos_hint">ميّز المستودعات بنجمة على GitHub التي تحتوي على إصدارات قابلة للتثبيت لتظهر هنا</string>
    <string name="last_synced">آخر مزامنة</string>
    <string name="just_now">الآن</string>
    <string name="minutes_ago">منذ %1$d دقيقة</string>
    <string name="hours_ago">منذ %1$d ساعة</string>
    <string name="days_ago">منذ %1$d يوم</string>
    <string name="dismiss">تجاهل</string>
    <string name="sync_starred_failed">فشلت مزامنة المستودعات المميزة بنجمة</string>


    <string name="failed_to_load_repositories">فشل تحميل المستودعات</string>
    <string name="failed_to_load_profile">فشل تحميل الملف الشخصي</string>

    <!-- Developer Profile - Stats -->
    <string name="repositories">المستودعات</string>
    <string name="followers">المتابعون</string>
    <string name="following">يتابع</string>

    <!-- Developer Profile - Filter & Sort -->
    <string name="search_repositories">البحث في المستودعات…</string>
    <string name="clear_search">مسح البحث</string>
    <string name="filter_with_releases">مع إصدارات</string>
    <string name="filter_installed">المثبتة</string>
    <string name="filter_favorites">المفضلة</string>
    <string name="sort">ترتيب</string>
    <string name="sort_recently_updated">المحدّث مؤخراً</string>
    <string name="sort_name">الاسم</string>
    <string name="sort_recently_added">أُضيف مؤخراً</string>
    <string name="sort_selected">محدّد</string>

    <!-- Developer Profile - Repository Count -->
    <string name="repository_singular">مستودع</string>
    <string name="showing_x_of_y_repositories">عرض %1$d من %2$d مستودع</string>

    <!-- Developer Profile - Empty States -->
    <string name="no_repos_with_releases">لا توجد مستودعات بإصدارات قابلة للتثبيت</string>
    <string name="no_installed_repos">لا توجد مستودعات مثبتة</string>
    <string name="no_favorite_repos">لا توجد مستودعات مفضلة</string>

    <string name="has_release">يحتوي على إصدار</string>

    <string name="time_years_ago">منذ %1$d سنة</string>
    <string name="time_months_ago">منذ %1$d شهر</string>
    <string name="time_days_ago">منذ %1$d يوم</string>
    <string name="time_hours_ago">منذ %1$d ساعة</string>
    <string name="time_minutes_ago">منذ %1$d دقيقة</string>

    <!-- Developer Profile - Count Formatting -->
    <string name="count_millions">%1$d مليون</string>
    <string name="count_thousands">%1$d ألف</string>

    <string name="released_just_now">صدر للتو</string>
    <string name="released_hours_ago">صدر منذ %1$d ساعة</string>
    <string name="released_yesterday">صدر أمس</string>
    <string name="released_days_ago">صدر منذ %1$d يوم</string>
    <string name="released_on_date">صدر في %1$s</string>

    <string name="bottom_nav_home_title">الرئيسية</string>
    <string name="bottom_nav_search_title">البحث</string>
    <string name="bottom_nav_apps_title">المكتبة</string>
    <string name="bottom_nav_profile_title">الملف الشخصي</string>

    <string name="forked_repository">نسخة متفرعة</string>

    <!-- Version picker -->
    <string name="category_stable">مستقر</string>
    <string name="category_pre_release">إصدار تجريبي</string>
    <string name="category_all">الكل</string>
    <string name="select_version">اختر الإصدار</string>
    <string name="pre_release_badge">تجريبي</string>
    <string name="latest_badge">الأحدث</string>
    <string name="no_version_selected">لا يوجد إصدار</string>
    <string name="versions_title">الإصدارات</string>

    <!-- Apps feature - Last checked -->
    <string name="last_checked">آخر فحص: %1$s</string>
    <string name="last_checked_just_now">الآن</string>
    <string name="last_checked_minutes_ago">منذ %1$d دقيقة</string>
    <string name="last_checked_hours_ago">منذ %1$d ساعة</string>
    <string name="checking_for_updates">جارٍ التحقق من التحديثات…</string>


    <!-- Profile section -->
    <string name="profile_sign_in_title">تسجيل الدخول إلى GitHub</string>
    <string name="profile_sign_in_description">افتح التجربة الكاملة. أدر تطبيقاتك، زامن تفضيلاتك، وتصفح بشكل أسرع.</string>
    <string name="profile_repos">المستودعات</string>
    <string name="profile_login">تسجيل الدخول</string>
    <string name="profile_stars_description">مستودعاتك المميزة بنجمة من GitHub</string>
    <string name="profile_favourites_description">مستودعاتك المفضلة المحفوظة محلياً</string>

    <!-- Session expired dialog -->
    <string name="session_expired_title">انتهت الجلسة</string>
    <string name="session_expired_message">انتهت جلسة GitHub الخاصة بك أو تم إلغاء الرمز المميز. يرجى تسجيل الدخول مرة أخرى لمتابعة استخدام الميزات المصادق عليها.</string>
    <string name="session_expired_hint">لا يزال بإمكانك التصفح كضيف مع طلبات API محدودة.</string>
    <string name="sign_in_again">تسجيل الدخول مرة أخرى</string>
    <string name="continue_as_guest">المتابعة كضيف</string>

    <!-- Logout improvements -->
    <string name="logout_revocation_note">سيؤدي هذا إلى مسح جلستك المحلية والبيانات المخزنة مؤقتاً. لإلغاء الوصول بالكامل، قم بزيارة إعدادات GitHub > التطبيقات.</string>

    <string name="auth_error_code_expired">انتهت صلاحية رمز الجهاز.</string>
    <string name="auth_hint_try_again">يرجى محاولة تسجيل الدخول مرة أخرى للحصول على رمز جديد.</string>
    <string name="auth_hint_check_connection">يرجى التحقق من اتصالك بالإنترنت والمحاولة مرة أخرى.</string>
    <string name="auth_hint_denied">لقد رفضت طلب التفويض. حاول مرة أخرى إذا كان ذلك غير مقصود.</string>
    <string name="auth_check_status">لقد قمت بالتفويض بالفعل</string>
    <string name="auth_polling_status">جارٍ التحقق…</string>
    <string name="auth_rate_limited">تم تقييد المعدل — إعادة المحاولة خلال %1$d ثانية</string>

    <!-- Read More / Show Less -->
    <string name="read_more">اقرأ المزيد</string>
    <string name="show_less">عرض أقل</string>

    <string name="share_repository">مشاركة المستودع</string>
    <string name="failed_to_share_link">فشل مشاركة الرابط</string>
    <string name="link_copied_to_clipboard">تم نسخ الرابط إلى الحافظة</string>

    <string name="translate_to">ترجمة إلى…</string>
    <string name="search_language">البحث عن لغة</string>
    <string name="translation_failed">فشلت الترجمة. يرجى المحاولة مرة أخرى.</string>

    <!-- Search - GitHub Link -->
    <string name="open_github_link">فتح رابط GitHub</string>
    <string name="clipboard_link_detected">تم اكتشاف رابط GitHub في الحافظة</string>
    <string name="detected_links">الروابط المكتشفة</string>
    <string name="open_in_app">فتح في التطبيق</string>
    <string name="no_github_link_in_clipboard">لم يتم العثور على رابط GitHub في الحافظة</string>

    <string name="clear">مسح</string>















    <string name="installer_type_default">الافتراضي</string>
    <string name="installer_type_default_description">نافذة التثبيت القياسية للنظام</string>
    <string name="installer_type_shizuku">Shizuku</string>
    <string name="installer_type_shizuku_description">تثبيت صامت بدون مطالبات</string>
    <string name="shizuku_status_not_installed">Shizuku غير مثبت</string>
    <string name="shizuku_status_not_running">Shizuku لا يعمل</string>
    <string name="shizuku_status_permission_needed">يتطلب إذنًا</string>
    <string name="shizuku_status_ready">جاهز</string>
    <string name="shizuku_grant_permission">منح الإذن</string>
    <string name="shizuku_install_hint">ثبّت Shizuku لتفعيل التثبيت الصامت</string>
    <string name="shizuku_start_hint">شغّل Shizuku لتفعيل التثبيت الصامت</string>
    <string name="shizuku_install_failed_fallback">فشل تثبيت Shizuku، يتم استخدام المثبت القياسي</string>

    <string name="auto_update_title">تحديث التطبيقات تلقائيًا</string>
    <string name="auto_update_description">تنزيل التحديثات وتثبيتها تلقائيًا في الخلفية عبر Shizuku</string>

    <string name="update_check_interval_title">فترة التحقق من التحديثات</string>
    <string name="update_check_interval_description">عدد مرات التحقق من تحديثات التطبيق في الخلفية</string>
    <string name="update_check_enabled_title">التحقق التلقائي من التحديثات</string>
    <string name="update_check_enabled_description">يبحث عن التحديثات في الخلفية بشكل دوري. أوقفه لتوفير البطارية — يمكنك دائماً التحقق يدوياً من شاشة تفاصيل أي تطبيق.</string>
    <string name="battery_optimization_card_title">السماح بالتحديثات في الخلفية</string>
    <string name="battery_optimization_card_description">جهازك يوقف المهام الخلفية بقوة. أضف Komi Store إلى قائمة الاستثناء من تحسين البطارية حتى تعمل عمليات فحص التحديثات والتثبيت الصامت بشكل موثوق.</string>
    <string name="battery_optimization_card_open">فتح الإعدادات</string>
    <string name="battery_optimization_card_dismiss">ربما لاحقاً</string>

    <string name="add_by_link">تتبّع تطبيقًا</string>
    <string name="link_app_title">ربط التطبيق بالمستودع</string>
    <string name="pick_installed_app">اختر تطبيقاً مثبتاً لربطه بمستودع GitHub</string>
    <string name="search_apps_hint">البحث عن التطبيقات…</string>
    <string name="enter_repo_url">رابط مستودع GitHub</string>
    <string name="repo_url_hint">github.com/owner/repo</string>
    <string name="validating_repo">جارٍ التحقق…</string>
    <string name="link_and_track">ربط وتتبع</string>
    <string name="checking_release">التحقق من آخر إصدار…</string>
    <string name="verifying_signing_key">التحقق من مفتاح التوقيع…</string>
    <string name="package_name_mismatch">عدم تطابق اسم الحزمة: ملف APK هو %1$s، لكن التطبيق المحدد هو %2$s</string>
    <string name="signing_key_mismatch_link">عدم تطابق مفتاح التوقيع: ملف APK في هذا المستودع موقّع من مطور مختلف</string>
    <string name="select_asset_title">اختر المثبّت</string>
    <string name="select_asset_description">اختر ملف APK للتحقق من مطابقته للتطبيق المثبت</string>
    <string name="export_apps">تصدير</string>
    <string name="import_apps">استيراد</string>
    <string name="include_pre_releases_title">قناة البيتا الافتراضية</string>
    <string name="include_pre_releases_description">تشمل التطبيقات التي تتعقبها حديثاً إصدارات البيتا افتراضياً. التطبيقات المتعقَّبة مسبقاً تحتفظ بإعدادها الخاص (بدّله من شاشة التفاصيل).</string>
    <string name="confirm_uninstall_title">إلغاء تثبيت التطبيق؟</string>
    <string name="confirm_uninstall_message">هل أنت متأكد من إلغاء تثبيت %1$s؟ لا يمكن التراجع عن هذا الإجراء وقد تُفقد بيانات التطبيق.</string>
    <string name="invalid_github_url">رابط GitHub غير صالح. استخدم التنسيق: github.com/owner/repo</string>
    <string name="repo_not_found">المستودع غير موجود: %1$s/%2$s</string>
    <string name="rate_limit_try_again">تم تجاوز حد طلبات GitHub API. حاول لاحقاً.</string>
    <string name="failed_to_link">فشل الربط: %1$s</string>
    <string name="failed_to_load_apps">فشل تحميل التطبيقات المثبتة</string>
    <string name="app_linked_success">تم ربط %1$s بـ %2$s/%3$s</string>
    <string name="export_failed">فشل التصدير: %1$s</string>
    <string name="import_failed">فشل الاستيراد: %1$s</string>
    <string name="signing_key_changed_title">تغيّر مفتاح التوقيع</string>
    <string name="signing_key_changed_message">تغيّرت شهادة توقيع هذا التطبيق منذ تثبيته لأول مرة.\n\nقد يعني هذا أن المطور غيّر مفتاح التوقيع، أو أن الملف قد تم التلاعب به.\n\nالمتوقع: %1$s\nالمستلم: %2$s</string>
    <string name="install_anyway">التثبيت على أي حال</string>
    <string name="verified_build">بناء موثق</string>
    <string name="checking_attestation">جارٍ التحقق\u2026</string>
    <string name="assets_title">الملفات</string>
    <string name="no_assets_selected">لا توجد ملفات</string>
    <string name="no_assets_in_list">لا توجد ملفات مرتبطة بهذا الإصدار</string>
    <string name="assets_selection_label">اختر خيار الملف</string>
    <string name="multiple_assets_info_dialog_title">ملفات متعددة متاحة</string>
    <string name="multiple_assets_info_dialog_text">تتوفر عدة ملفات قابلة للتثبيت لهذا الإصدار. يرجى مراجعة القائمة واختيار الملف المناسب لجهازك.</string>
    <string name="icon_content_description_info">معلومات</string>
    <string name="select_language">اختر اللغة</string>
    <string name="update_package_mismatch">عدم تطابق الحزمة: ملف APK هو %1$s، لكن التطبيق المثبت هو %2$s. تم حظر التحديث.</string>
    <string name="update_signing_key_mismatch">عدم تطابق مفتاح التوقيع: تم توقيع التحديث بواسطة مطور مختلف. تم حظر التحديث.</string>

    <string name="scrollbar_option_title">شريط التمرير</string>
    <string name="scrollbar_option_description">إظهار شريط التمرير في القوائم القابلة للتمرير (سطح المكتب)</string>
    <string name="content_width_title">عرض المحتوى</string>
    <string name="content_width_description">يتحكم في الحد الأقصى لعرض عمود شاشة التفاصيل (سطح المكتب)</string>
    <string name="content_width_compact">ضيّق</string>
    <string name="content_width_wide">واسع</string>
    <string name="content_width_extra_wide">واسع جدًا</string>

    <string name="seen_history_cleared">تم مسح سجل المشاهدة</string>
    <string name="seen_badge">تمت المشاهدة</string>
    <string name="self_owned_badge">هذا المستودع لك</string>
    <string name="hide_repository">إخفاء المستودع</string>

    <string name="recently_viewed">تمت مشاهدته مؤخرًا</string>
    <string name="profile_recently_viewed_description">المستودعات التي قمت بزيارتها</string>
    <string name="delete_all">حذف الكل</string>
    <string name="delete_downloads_confirmation_title">حذف جميع التنزيلات؟</string>
    <string name="delete_downloads_confirmation_message">سيؤدي هذا إلى حذف جميع ملفات APK والمثبتات نهائيًا (%1$s). يمكنك إعادة تنزيلها في أي وقت.</string>
    <string name="downloads_cleared">تم حذف جميع الحزم التي تم تنزيلها.</string>
    <string name="unable_to_verify_attestation">تعذر التحقق</string>

    <string name="recent_searches">عمليات البحث الأخيرة</string>
    <string name="clear_all_history">مسح الكل</string>
    <string name="remove_search_history_item">إزالة</string>

    <string name="tweaks_title">تعديلات</string>

    <!-- Monorepo support -->
    <string name="asset_filter_label">عامل تصفية الأصول</string>
    <string name="asset_filter_placeholder">مثال: ente-auth</string>
    <string name="asset_filter_help">سيتم تثبيت الأصول المطابقة لهذا النمط (regex) فقط. مفيد للمستودعات التي تحتوي على عدة تطبيقات.</string>
    <string name="asset_filter_invalid">تعبير عادي غير صالح</string>
    <string name="asset_filter_no_match">لا توجد أصول مطابقة لهذا الفلتر</string>
    <string name="asset_none_available">لا توجد أصول قابلة للتثبيت في هذا الإصدار</string>
    <plurals name="asset_filter_visible_count">
        <item quantity="one">عرض %1$d من %2$d أصل</item>
        <item quantity="other">عرض %1$d من %2$d أصل</item>
    </plurals>
    <string name="fallback_older_releases_title">الرجوع إلى الإصدارات الأقدم</string>
    <string name="fallback_older_releases_description">المرور عبر الإصدارات السابقة حتى يتطابق أحدها مع الفلتر. مطلوب للمستودعات التي يكون فيها أحدث إصدار لتطبيق آخر.</string>
    <string name="advanced_settings_title">فلتر متقدم</string>
    <string name="advanced_settings_description">قم بضبط كيفية مطابقة هذا التطبيق في المستودع. استخدم هذه الإعدادات عندما يحتوي المستودع على عدة تطبيقات.</string>
    <string name="advanced_settings_open">فتح الفلتر المتقدم</string>
    <string name="advanced_save">حفظ</string>
    <string name="advanced_preview_title">معاينة</string>
    <string name="advanced_preview_refresh">تحديث المعاينة</string>
    <string name="advanced_preview_pending">اكتب فلترًا لمعاينة الأصول المطابقة.</string>
    <string name="advanced_preview_no_match">لا توجد إصدارات حديثة تحتوي على أصول مطابقة. حاول تفعيل الرجوع إلى الإصدارات الأقدم أو ضبط النمط.</string>
    <string name="advanced_preview_failed">تعذر تحميل المعاينة. تحقق من اتصالك وحاول مرة أخرى.</string>
    <plurals name="advanced_preview_release">
        <item quantity="one">مطابقة في %1$s · %2$d أصل</item>
        <item quantity="other">مطابقة في %1$s · %2$d أصل</item>
    </plurals>

    <!-- Preferred-variant feature -->
    <string name="variant_picker_title">النوع المفضل</string>
    <string name="variant_picker_description">اختر نوع APK الذي يجب تثبيته للتحديثات. يتم تذكر الاختيار عبر الإصدارات.</string>
    <string name="variant_picker_no_assets">لا توجد أصول قابلة للتثبيت في أحدث إصدار.</string>
    <string name="variant_picker_no_pinnable">لا تحتوي هذه النسخة على أنواع موسومة بالإصدار يمكن تثبيتها. سيستمر المحدد التلقائي في اختيار أفضل أصل لجهازك.</string>
    <string name="variant_picker_load_failed">تعذر تحميل الأنواع. تحقق من اتصالك وحاول مرة أخرى.</string>
    <string name="variant_picker_save_failed">تعذر حفظ اختيارك. حاول مرة أخرى.</string>
    <string name="variant_picker_stale_title">تغير النوع — اختر مرة أخرى</string>
    <string name="variant_picker_stale_was">كان: %1$s</string>
    <string name="variant_picker_auto_title">تلقائي</string>
    <string name="variant_picker_auto_subtitle">دع Komi Store يختار أفضل نوع لجهازك</string>
    <string name="markdown_alert_note">ملاحظة</string>
    <string name="markdown_alert_tip">نصيحة</string>
    <string name="markdown_alert_important">مهم</string>
    <string name="markdown_alert_warning">تحذير</string>
    <string name="markdown_alert_caution">تنبيه</string>
    <string name="variant_picker_pinned">مثبت على: %1$s</string>
    <string name="variant_stale_hint">تغير النوع — انقر تحديث للاختيار مرة أخرى</string>
    <string name="variant_label_inline">النوع: %1$s</string>
    <string name="variant_picker_unpin">إلغاء التثبيت</string>
    <string name="variant_picker_pinned_badge">مثبت</string>
    <string name="variant_picker_open">اختيار النوع</string>
    <string name="variant_picker_open_filter">تعديل التصفية</string>
    <string name="variant_first_pin_toast">سوف تفضل التحديثات المستقبلية النوع %1$s. غيّر هذا في أي وقت من إعدادات التطبيق.</string>
    <string name="variant_first_pin_toast_generic">سوف تفضل التحديثات المستقبلية هذا النوع. غيّر هذا في أي وقت من إعدادات التطبيق.</string>
    <string name="variant_unpinned_toast">تم إلغاء تثبيت النوع. ستستخدم التحديثات المنتقي التلقائي.</string>
    <string name="advanced_filter_variant_relation">يحدد المرشّح الملفات التي يتم النظر فيها. يحدد تثبيت النوع أيها سيتم تثبيته.</string>
    <string name="install">تثبيت</string>
    <string name="ready_to_install">جاهز للتثبيت</string>
    <string name="install_ready">تثبيت (جاهز)</string>

    <string name="translation_intro">اختر الخدمة المستخدمة لترجمة README.</string>
    <string name="translation_provider_title">خدمة الترجمة</string>
    <string name="translation_provider_description">يعمل Google عالميًا دون تهيئة. يعمل Youdao من الصين القارية ولكنه يتطلب بيانات اعتماد API من بوابة مطوري Youdao.</string>
    <string name="translation_provider_google">Google</string>
    <string name="translation_provider_youdao">Youdao</string>
    <string name="translation_provider_saved">تم تحديث خدمة الترجمة</string>
    <string name="translation_youdao_help">سجّل في ai.youdao.com للحصول على App Key و App Secret. الطبقة المجانية كافية للاستخدام العادي.</string>
    <string name="translation_youdao_app_key">App Key</string>
    <string name="translation_youdao_app_secret">App Secret</string>
    <string name="translation_youdao_save">حفظ بيانات الاعتماد</string>
    <string name="translation_youdao_saved">تم حفظ بيانات اعتماد Youdao</string>

    <!-- Releases status card -->
    <string name="releases_load_failed">تعذّر تحميل الإصدارات</string>
    <string name="releases_load_failed_description">تحقق من اتصالك وحاول مرة أخرى.</string>
    <string name="no_releases_published">لم يتم نشر أي إصدارات بعد</string>
    <string name="loading_releases">جارٍ تحميل الإصدارات…</string>

    <!-- Personal Access Token sign-in -->
    <string name="pat_use_token_instead">هل تواجه مشكلة؟ استخدم Personal Access Token</string>
    <string name="auth_use_device_code_instead">استخدم رمز الجهاز بدلاً من ذلك</string>
    <string name="installer_category_side_store">F-Droid / Obtainium</string>
    <string name="installer_category_sideloaded">تثبيت يدوي</string>
    <string name="installer_category_vendor_store">متجر المُصنّع</string>
    <string name="installer_category_play_store">متجر Play</string>
    <string name="installer_category_system_update">تحديث النظام</string>
    <string name="link_smart_search_title">ابحث عن مستودع مطابق</string>
    <string name="link_smart_search_searching">جارٍ البحث عن تطابق على GitHub…</string>
    <string name="link_smart_search_no_matches">لم يتم العثور على تطابق تلقائي.</string>
    <string name="link_smart_search_failed">تعذّر البحث عن التطابقات.</string>
    <string name="link_smart_search_enter_manually">إدخال العنوان يدوياً</string>
    <string name="match_source_manifest">البيان</string>
    <string name="match_source_fingerprint">التوقيع</string>
    <string name="match_source_search">بحث</string>
    <string name="match_source_manual">يدوي</string>
    <string name="match_source_starred">بنجمة</string>
    <string name="pat_sheet_title">تسجيل الدخول باستخدام Personal Access Token</string>
    <string name="pat_sheet_description">أنشئ Personal Access Token (classic أو fine-grained) على أي جهاز يمكنه الوصول إلى GitHub، ثم الصقه أدناه. يتطلب صلاحية قراءة للمستودعات وملفك الشخصي.</string>
    <string name="pat_open_settings">فتح إعدادات رموز GitHub</string>
    <string name="pat_input_label">Personal Access Token</string>
    <string name="pat_input_placeholder">ghp_… أو github_pat_…</string>
    <string name="pat_submit">تسجيل الدخول</string>
    <string name="pat_cancel">إلغاء</string>
    <string name="pat_error_empty">يرجى لصق رمز.</string>
    <string name="pat_error_invalid_format">هذا لا يبدو كرمز GitHub. تبدأ الرموز بـ ghp_ أو github_pat_.</string>
    <string name="pat_error_bad_credentials">هذا الرمز غير صالح أو تم إلغاؤه.</string>
    <string name="pat_error_insufficient_scope">هذا الرمز لا يمتلك الصلاحيات المطلوبة.</string>
    <string name="pat_error_generic">تعذّر حفظ الرمز. يرجى المحاولة مرة أخرى.</string>

    <!-- E10 — Apps sort -->
    <string name="sort_apps">ترتيب التطبيقات</string>
    <string name="sort_updates_first">التحديثات أولاً</string>

    <!-- Pre-release channel UX -->
    <string name="channel_chip_include_betas">تضمين الإصدارات التجريبية</string>
    <string name="channel_chip_stable_only">الإصدار المستقر فقط</string>
    <string name="channel_chip_coachmark_title">اختر قناة الإصدار</string>
    <string name="channel_chip_coachmark_body">اضغط للتبديل بين الإصدارات المستقرة وإصدارات البيتا لهذا التطبيق.</string>
    <string name="channel_chip_coachmark_dismiss">حسناً</string>
    <string name="action_switch_to_stable">التبديل إلى الإصدار المستقر %1$s</string>
    <string name="stalled_project_warning_months">لا يوجد إصدار مستقر منذ %1$d أشهر</string>
    <string name="stalled_project_warning_days">لا يوجد إصدار مستقر منذ %1$d أيام</string>
    <string name="stalled_project_warning_description">إصدارات تجريبية نشطة لكن المشروع لم يُصدر بناءً مستقراً منذ فترة. قد لا تتقارب الإصدارات التجريبية إلى إصدار مستقر.</string>
    <string name="merged_whats_changed_title">ما الذي تغيّر منذ %1$s</string>

    <!-- E1 — External import wizard -->
    <string name="external_import_top_bar_title">استيراد التطبيقات المثبّتة</string>
    <string name="external_import_top_bar_back">رجوع</string>
    <string name="external_import_overflow_more">خيارات أخرى</string>
    <string name="external_import_overflow_skip_remaining">تخطي الباقي</string>
    <string name="external_import_progress_scanning">جارٍ فحص تطبيقاتك…</string>
    <string name="external_import_progress_auto_importing">جارٍ استيراد التطابقات…</string>
    <string name="external_import_progress_working">جارٍ العمل…</string>
    <plurals name="external_import_progress_subtitle_count">
        <item quantity="zero">لم نفحص أي تطبيق</item>
        <item quantity="one">فحصنا تطبيقاً واحداً</item>
        <item quantity="two">فحصنا تطبيقين</item>
        <item quantity="few">فحصنا %1$d تطبيقات</item>
        <item quantity="many">فحصنا %1$d تطبيقاً</item>
        <item quantity="other">فحصنا %1$d تطبيق</item>
    </plurals>
    <string name="external_import_card_action_skip">تخطي</string>
    <string name="external_import_card_action_link">ربط</string>
    <string name="external_import_card_action_more">المزيد من التطابقات</string>
    <string name="external_import_card_action_less">إخفاء التطابقات</string>
    <string name="external_import_card_installer_chip">مثبّت عبر %1$s</string>
    <string name="external_import_card_preselect_unknown">اضغط للبحث عن مستودع</string>
    <string name="external_import_card_expand_label">توسيع لرؤية تطابقات أخرى</string>
    <string name="external_import_card_collapse_label">طي البطاقة</string>
    <string name="external_import_search_icon_label">البحث في GitHub</string>
    <string name="external_import_search_empty">لا توجد تطابقات</string>
    <string name="external_import_search_error_default">فشل البحث</string>
    <string name="external_import_search_placeholder_url">الصق رابط github.com أو ابحث…</string>
    <plurals name="external_import_completion_headline">
        <item quantity="zero">لا يوجد تطبيق يتم تتبعه الآن.</item>
        <item quantity="one">يتم تتبع تطبيق واحد الآن.</item>
        <item quantity="two">يتم تتبع تطبيقين الآن.</item>
        <item quantity="few">يتم تتبع %1$d تطبيقات الآن.</item>
        <item quantity="many">يتم تتبع %1$d تطبيقاً الآن.</item>
        <item quantity="other">يتم تتبع %1$d تطبيق الآن.</item>
    </plurals>
    <string name="external_import_completion_skipped_subline">تم تخطي %1$d — يمكنك إعادة تشغيل الفحص من الإعدادات.</string>
    <string name="external_import_completion_action_view_all">عرض الكل</string>
    <string name="external_import_empty_all_matched">تمت مطابقة الكل.\nلا يوجد شيء للربط.</string>
    <string name="external_import_empty_done">تم</string>
    <string name="external_import_empty_no_apps_title">لم نتمكن من العثور على أي تطبيقات GitHub على هذا الجهاز.</string>
    <string name="external_import_empty_no_apps_body">هذا يعني إما أن كل شيء تم تثبيته عبر متجر مختلف، أو أننا لا نملك صلاحية رؤية ما هو مثبّت.</string>
    <string name="external_import_empty_grant_permission">منح الإذن</string>
    <string name="external_import_empty_ok">حسناً</string>
    <string name="external_import_empty_add_manually">إضافة تطبيق من متجر آخر</string>
    <string name="external_import_permission_title">ابحث عن تطبيقات GitHub الخاصة بك</string>
    <string name="external_import_permission_body">يمكننا فحص تطبيقاتك المثبّتة ومطابقتها مع إصدارات GitHub — حتى تعمل التحديثات والكشف تلقائياً.\n\nللقيام بذلك، نحتاج إلى معرفة التطبيقات التي لديك. بدون الإذن يمكننا رؤية نحو 5 تطبيقات فقط؛ معه يمكننا رؤية جميعها.\n\nنحن لا نرسل قائمة تطبيقاتك إلى أي مكان دون إذنك. تعمل المطابقة على جهازك. البحث الاختياري في الخادم يرسل فقط اسم الحزمة وتسمية التطبيق، وعند توفرها بصمة التوقيع ومصدر التثبيت وأي تلميح لمستودع GitHub مُعلَن في بيان التطبيق — وليس قائمة كاملة بما هو مثبّت.</string>
    <string name="external_import_permission_continue">متابعة</string>
    <string name="external_import_permission_not_now">ليس الآن</string>
    <plurals name="external_import_proposal_banner_headline">
        <item quantity="zero">لم نجد أي تطبيق من GitHub</item>
        <item quantity="one">وجدنا تطبيقاً واحداً من GitHub</item>
        <item quantity="two">وجدنا تطبيقين من GitHub</item>
        <item quantity="few">وجدنا %1$d تطبيقات من GitHub</item>
        <item quantity="many">وجدنا %1$d تطبيقاً من GitHub</item>
        <item quantity="other">وجدنا %1$d تطبيق من GitHub</item>
    </plurals>
    <string name="external_import_proposal_banner_body">راجعها لتتبع التحديثات هنا.</string>
    <string name="external_import_proposal_banner_review">مراجعة</string>
    <string name="external_import_proposal_banner_dismiss">تجاهل</string>
    <string name="external_import_match_confidence_a11y">درجة ثقة التطابق: %1$d بالمئة</string>
    <string name="external_import_match_confidence_chip">%1$d</string>
    <string name="external_import_error_link_failed">تعذّر ربط هذا التطبيق — حاول مجدداً.</string>
    <string name="external_import_error_link_network">تعذّر الوصول إلى GitHub. حاول مجدداً لاحقاً.</string>
    <string name="external_import_error_scan_failed_default">فشل الفحص</string>
    <string name="external_import_installer_obtainium">Obtainium</string>
    <string name="external_import_installer_fdroid">F-Droid</string>
    <string name="external_import_installer_browser">المتصفح</string>
    <string name="external_import_installer_sideload">Sideload</string>
    <string name="external_import_installer_self">Komi Store</string>
    <string name="external_import_installer_unknown">مصدر غير معروف</string>
    <string name="external_import_undo_linked">تم ربط %1$s.</string>
    <string name="external_import_undo_skipped">تم تخطي %1$s.</string>
    <string name="external_import_undo_action">تراجع</string>
    <string name="external_import_undo_failed">تعذّر التراجع — حاول مجدداً.</string>
    <plurals name="external_import_list_remaining">
        <item quantity="zero">لا يوجد تطبيق للمراجعة</item>
        <item quantity="one">تطبيق واحد للمراجعة</item>
        <item quantity="two">تطبيقان للمراجعة</item>
        <item quantity="few">%1$d تطبيقات للمراجعة</item>
        <item quantity="many">%1$d تطبيقاً للمراجعة</item>
        <item quantity="other">%1$d تطبيق للمراجعة</item>
    </plurals>
    <string name="external_import_list_add_manually">لا ترى تطبيقك؟ أضفه يدوياً</string>
    <plurals name="external_import_auto_summary_headline">
        <item quantity="zero">لم يتم ربط أي تطبيق تلقائياً</item>
        <item quantity="one">تم ربط تطبيق واحد تلقائياً</item>
        <item quantity="two">تم ربط تطبيقين تلقائياً</item>
        <item quantity="few">تم ربط %1$d تطبيقات تلقائياً</item>
        <item quantity="many">تم ربط %1$d تطبيقاً تلقائياً</item>
        <item quantity="other">تم ربط %1$d تطبيق تلقائياً</item>
    </plurals>
    <string name="external_import_auto_summary_body">لقد تعرّفنا عليها بثقة عالية. يمكنك التراجع عن تطابقات فردية من تفاصيل كل تطبيق، أو التراجع عن الكل الآن.</string>
    <plurals name="external_import_auto_summary_review_hint">
        <item quantity="zero">لا يوجد المزيد يحتاج إلى مدخلاتك.</item>
        <item quantity="one">يحتاج %1$d آخر إلى مدخلاتك.</item>
        <item quantity="two">يحتاج %1$d آخران إلى مدخلاتك.</item>
        <item quantity="few">تحتاج %1$d أخرى إلى مدخلاتك.</item>
        <item quantity="many">يحتاج %1$d آخر إلى مدخلاتك.</item>
        <item quantity="other">يحتاج %1$d إلى مدخلاتك.</item>
    </plurals>
    <string name="external_import_auto_summary_continue">متابعة</string>
    <string name="external_import_auto_summary_undo_all">التراجع عن الكل</string>
    <string name="external_import_auto_summary_more_count">+%1$d أخرى</string>
    <string name="external_import_rescan_menu">فحص تطبيقات GitHub</string>

    <!-- E1 — Details unlink dialog -->
    <string name="details_unlink_external_app_menu">إلغاء الربط بهذا المستودع</string>
    <string name="details_unlink_external_app_dialog_title">إلغاء ربط هذا التطبيق؟</string>
    <string name="details_unlink_external_app_dialog_body">سنتوقف عن تتبع %1$s كمثبّت من هذا المستودع. يبقى التطبيق على جهازك — يُزال الرابط فقط.</string>
    <string name="details_unlink_external_app_dialog_confirm">إلغاء الربط</string>
    <string name="details_unlink_external_app_success">تم إلغاء الربط. سنقترح تطابقاً مجدداً في الفحص التالي.</string>
    <string name="details_unlink_external_app_failure">تعذّر إلغاء الربط — حاول مجدداً.</string>
    <string name="details_linked_repo_banner_title">مرتبط بـ %1$s/%2$s</string>
    <string name="details_linked_repo_banner_body">ربط يدوي — متحقق منه من قِبلك. افصل الارتباط لإعادة الفحص.</string>

    <!-- Details manual refresh -->
    <string name="details_refresh">تحديث</string>
    <string name="details_refresh_cooldown">تحديث (%1$dث)</string>
    <string name="details_refresh_more_options">خيارات إضافية</string>
    <string name="details_refresh_snackbar_cooldown">لقد قمت بالتحديث للتو — حاول مرة أخرى خلال %1$d ثانية.</string>
    <string name="details_refresh_snackbar_budget_exhausted">خدمة التحديث مشغولة — حاول مرة أخرى خلال %1$d ثانية.</string>
    <string name="details_refresh_snackbar_archived">هذا المستودع مؤرشف على GitHub.</string>
    <string name="details_refresh_snackbar_not_found">لم يعد هذا المستودع موجوداً على GitHub.</string>
    <string name="details_refresh_snackbar_upstream">تعذر التحديث. حاول مرة أخرى لاحقاً.</string>
    <string name="details_refresh_snackbar_generic">فشل التحديث. حاول مرة أخرى.</string>

    <string name="feedback_title">إرسال ملاحظات</string>
    <string name="feedback_close">إغلاق</string>
    <string name="feedback_category_label">الفئة</string>
    <string name="feedback_category_bug">خطأ</string>
    <string name="feedback_category_feature">طلب ميزة</string>
    <string name="feedback_category_change">طلب تغيير</string>
    <string name="feedback_category_other">أخرى</string>
    <string name="feedback_topic_label">الموضوع</string>
    <string name="feedback_topic_install_update">التثبيت / التحديث</string>
    <string name="feedback_topic_search">البحث &amp; الاكتشاف</string>
    <string name="feedback_topic_details">تفاصيل المستودع</string>
    <string name="feedback_topic_auth">المصادقة &amp; الحساب</string>
    <string name="feedback_topic_ui">واجهة / تجربة المستخدم</string>
    <string name="feedback_topic_translation">الترجمة / اللغة</string>
    <string name="feedback_topic_performance">الأداء</string>
    <string name="feedback_topic_other">أخرى</string>
    <string name="feedback_field_title">العنوان</string>
    <string name="feedback_field_description">الوصف</string>
    <string name="feedback_field_steps">خطوات إعادة الإنتاج</string>
    <string name="feedback_field_expected_actual">المتوقع مقابل الفعلي</string>
    <string name="feedback_field_use_case">حالة الاستخدام</string>
    <string name="feedback_field_proposed_solution">الحل المقترح</string>
    <string name="feedback_field_current_behaviour">السلوك الحالي</string>
    <string name="feedback_field_desired_behaviour">السلوك المطلوب</string>
    <string name="feedback_diagnostics_header">التشخيصات</string>
    <string name="feedback_diagnostics_include">تضمين التشخيصات</string>
    <string name="feedback_send_via_email">إرسال بريد إلكتروني</string>
    <string name="feedback_send_via_github">فتح كمشكلة GitHub</string>
    <string name="feedback_send_success_email">شكراً — جارٍ فتح عميل البريد.</string>
    <string name="feedback_send_success_github">شكراً — جارٍ فتح المتصفح.</string>
    <string name="feedback_send_error">تعذّر فتح قناة الملاحظات: %1$s</string>

    <!-- Tweaks - Custom forges -->
    <string name="custom_forges_entry_label">منصّات مخصّصة</string>
    <string name="custom_forges_dialog_title">منصّات مخصّصة</string>
    <string name="custom_forges_dialog_help">أدخل اسم مضيف Forgejo أو Gitea (مثل git.example.com). سيقبل GHS روابط هذه المضيفات في نموذج الربط اليدوي.</string>
    <string name="custom_forges_add_button">إضافة</string>
    <string name="custom_forges_empty">لا توجد منصّات مخصّصة بعد.</string>
    <string name="done">تم</string>

    <string name="mirror_picker_title">مرآة التنزيل</string>
    <string name="mirror_picker_description">تُستخدم لتنزيل أصول الإصدار. تتجه مكالمات GitHub API دائماً مباشرة. يجب على معظم المستخدمين إبقاء هذا على GitHub المباشر.</string>
    <string name="mirror_section_official">رسمي</string>
    <string name="mirror_section_community">مجتمع</string>
    <string name="mirror_status_ok">%1$dms</string>
    <string name="mirror_status_degraded">%1$dms</string>
    <string name="mirror_status_down">(متوقف)</string>
    <string name="mirror_status_unknown">?</string>
    <string name="mirror_custom_label">مرآة مخصصة…</string>
    <string name="mirror_custom_dialog_title">مرآة مخصصة</string>
    <string name="mirror_custom_dialog_hint">https://your-mirror.example/{url}</string>
    <string name="mirror_custom_validation_https">يجب أن يبدأ القالب بـ https://</string>
    <string name="mirror_custom_validation_template">يجب أن يحتوي القالب على {url} مرة واحدة بالضبط</string>
    <string name="mirror_custom_save">حفظ</string>
    <string name="mirror_test_button">اختبار المحدد</string>
    <string name="mirror_test_success">تم الوصول في %1$dms</string>
    <string name="mirror_test_http_error">أرجعت المرآة %1$d</string>
    <string name="mirror_test_timeout">انتهت المهلة بعد 5 ثوانٍ</string>
    <string name="mirror_test_dns_fail">تعذّر حل اسم المضيف</string>
    <string name="mirror_test_other">فشل: %1$s</string>
    <string name="mirror_deploy_your_own_hint">كل المرايا معطّلة؟ يمكنك استضافة مرآتك الخاصة في 5 دقائق — راجع الوثائق.</string>
    <string name="mirror_removed_toast">%1$s لم يعد متاحاً، تم التبديل إلى GitHub المباشر.</string>

    <!-- ───── 1.8.1 backlog ───── -->
    <string name="add_from_starred_title">إضافة من المميزة بنجمة</string>
    <string name="announcements_acknowledge">قرأت هذا</string>
    <string name="announcements_acknowledged">تم الاطلاع</string>
    <string name="announcements_category_news">أخبار</string>
    <string name="announcements_category_privacy">الخصوصية</string>
    <string name="announcements_category_security">الأمان</string>
    <string name="announcements_category_status">الحالة</string>
    <string name="announcements_category_survey">استطلاعات</string>
    <string name="announcements_empty">لا شيء لمشاركته الآن.</string>
    <string name="announcements_mute_locked">لا يمكن تعطيله</string>
    <string name="announcements_mute_settings_title">إظهار العناصر من</string>
    <string name="announcements_open_mute_settings">فتح إعدادات الكتم</string>
    <string name="announcements_profile_description">أخبار واستطلاعات وإشعارات مهمة.</string>
    <string name="announcements_read_more">اقرأ المزيد</string>
    <string name="announcements_refresh_failed">تعذّر التحديث — يتم عرض العناصر المخزّنة.</string>
    <string name="announcements_severity_critical">حرج</string>
    <string name="announcements_severity_important">مهم</string>
    <string name="announcements_severity_info">معلومة</string>
    <string name="announcements_title">الإعلانات</string>
    <string name="announcements_view_details">عرض التفاصيل</string>
    <string name="apk_inspect_button_label">فحص APK</string>
    <string name="apk_inspect_coachmark_body">الأذونات والتوقيع والمكونات — اطّلع على ما يُعلنه ملف APK بدقّة.</string>
    <string name="apk_inspect_coachmark_dismiss">فهمت</string>
    <string name="apk_inspect_coachmark_title">ألقِ نظرة قبل التثبيت</string>
    <string name="apk_inspect_compatibility">التوافق</string>
    <string name="apk_inspect_components">المكوّنات</string>
    <string name="apk_inspect_debuggable">إصدار قابل للتصحيح — مريب إن كان هذا إصدار نهائي.</string>
    <string name="apk_inspect_empty">لا شيء لفحصه لهذا التطبيق بعد.</string>
    <string name="apk_inspect_file_info">الملف</string>
    <string name="apk_inspect_identity">الهوية</string>
    <string name="apk_inspect_min_sdk">الحد الأدنى من SDK</string>
    <string name="apk_inspect_permissions">الأذونات (%1$d)</string>
    <string name="apk_inspect_permissions_empty">لا أذونات معلنة.</string>
    <string name="apk_inspect_permissions_title">الأذونات</string>
    <string name="apk_inspect_protection_dangerous">حساس</string>
    <string name="apk_inspect_protection_normal">عادي</string>
    <string name="apk_inspect_protection_privileged">مميّز</string>
    <string name="apk_inspect_protection_signature">التوقيع</string>
    <string name="apk_inspect_protection_unknown">غير معروف</string>
    <string name="apk_inspect_section_activities">الأنشطة</string>
    <string name="apk_inspect_section_main_activity">النشاط الرئيسي</string>
    <string name="apk_inspect_section_receivers">المستقبِلات</string>
    <string name="apk_inspect_section_services">الخدمات</string>
    <string name="apk_inspect_signing">بصمة التوقيع</string>
    <string name="apk_inspect_size">الحجم</string>
    <string name="apk_inspect_source_file">ملف محفوظ</string>
    <string name="apk_inspect_source_installed">حزمة مثبّتة</string>
    <string name="apk_inspect_target_sdk">SDK المستهدف</string>
    <string name="apk_inspect_title">فحص APK</string>
    <string name="apk_inspect_version_code">الإصدار</string>
    <string name="apps_compact_more_actions">المزيد من الإجراءات لـ %1$s</string>
    <string name="apps_compact_status_filter_active">عامل تصفية المستودع الموحَّد مفعّل</string>
    <string name="apps_compact_status_pending_install">في انتظار التثبيت</string>
    <string name="apps_compact_status_pre_release_on">إصدار مسبق مفعّل</string>
    <string name="apps_compact_status_ready_to_install">جاهز للتثبيت</string>
    <string name="apps_compact_status_updates_ignored">تم تجاهل التحديثات</string>
    <string name="apps_compact_status_variant_pinned">المتغيّر مثبَّت</string>
    <string name="apps_compact_status_variant_stale">المتغيّر قديم، يلزم اتخاذ إجراء</string>
    <string name="apps_ignore_updates">تجاهل التحديثات</string>
    <string name="apps_section_collapse">طي القسم</string>
    <string name="apps_section_count_suffix">· %1$d</string>
    <string name="apps_section_expand">توسيع القسم</string>
    <string name="apps_section_state_collapsed">مطوي</string>
    <string name="apps_section_state_expanded">موسّع</string>
    <string name="apps_section_up_to_date">محدَّث</string>
    <string name="confirm_discard_pending_message">إسقاط المثبِّت المحفوظ لـ %1$s وإزالة الصف من قائمة تطبيقاتك؟ سيتم حذف ملف APK الذي تم تنزيله.</string>
    <string name="confirm_discard_pending_title">إسقاط التثبيت المعلّق؟</string>
    <string name="dhizuku_grant_permission">منح الإذن</string>
    <string name="dhizuku_install_hint">ثبّت Dhizuku وفعّله كمالك للجهاز لتمكين التثبيت الصامت</string>
    <string name="dhizuku_start_hint">فعّل Dhizuku كمالك للجهاز لتمكين التثبيت الصامت</string>
    <string name="installer_type_root">روت</string>
    <string name="installer_type_root_description">تثبيت صامت عبر Magisk أو KernelSU أو APatch</string>
    <string name="root_status_ready">ممنوح</string>
    <string name="root_status_permission_needed">السماح بالروت</string>
    <string name="root_status_unavailable">لا يوجد روت</string>
    <string name="root_grant_permission">السماح بالوصول كروت</string>
    <string name="root_unavailable_hint">الروت غير متاح على هذا الجهاز. ثبّت Magisk أو KernelSU أو APatch أولاً.</string>
    <string name="dhizuku_status_not_installed">Dhizuku غير مثبّت</string>
    <string name="dhizuku_status_not_running">Dhizuku غير نشط</string>
    <string name="dhizuku_status_permission_needed">الإذن مطلوب</string>
    <string name="dhizuku_status_ready">جاهز</string>
    <string name="discard_pending_install">إسقاط</string>
    <string name="error_state_go_back">رجوع</string>
    <string name="error_state_subtitle_generic">تعذّر تحميل هذا المستودع. استخدم زر إعادة المحاولة بالأسفل.</string>
    <string name="error_state_subtitle_not_found">ربما يكون المستودع خاصاً أو أُعيدت تسميته أو حُذف.</string>
    <string name="error_state_subtitle_offline">تحقّق من اتصالك وأعد المحاولة.</string>
    <string name="error_state_subtitle_rate_limit">تجاوز GitHub أو خادمنا الحصة. أعد المحاولة بعد قليل.</string>
    <string name="error_state_title_generic">حدث خطأ ما</string>
    <string name="error_state_title_not_found">المستودع غير موجود</string>
    <string name="error_state_title_offline">أنت غير متصل</string>
    <string name="error_state_title_rate_limit">تم بلوغ حد الطلبات</string>
    <string name="export_apps_obtainium">تصدير لـ Obtainium</string>
    <string name="external_import_card_owner_byline">بواسطة %1$s</string>
    <string name="external_import_card_preselect_known_prefix">نعتقد أن هذا</string>
    <string name="failed_to_discard_pending">تعذّر إسقاط التثبيت المعلّق لـ %1$s</string>
    <string name="import_summary_already_tracked">%1$d متتبَّع مسبقاً</string>
    <string name="import_summary_close">تم</string>
    <string name="import_summary_collapse">إخفاء التفاصيل</string>
    <string name="import_summary_expand">عرض التفاصيل</string>
    <string name="import_summary_failed">%1$d فشل</string>
    <string name="import_summary_format_native">Komi Store</string>
    <string name="import_summary_format_obtainium">Obtainium</string>
    <string name="import_summary_imported">%1$d تم استيراده</string>
    <string name="import_summary_non_github">%1$d ليست GitHub</string>
    <string name="import_summary_non_github_caption">لا نتتبّع GitLab أو F-Droid أو مصادر HTML بعد.</string>
    <string name="import_summary_title">نتائج الاستيراد — %1$s</string>
    <string name="import_summary_unknown_caption">لا يبدو أنه ملف تصدير من Komi Store أو Obtainium. هذه بداية الملف:</string>
    <string name="import_summary_unknown_format">تعذّر قراءة هذا الملف</string>
    <string name="installer_attribution_custom_apply">تطبيق</string>
    <string name="installer_attribution_custom_error">استخدم اسم حزمة Android صالحاً (مثل com.example.installer)</string>
    <string name="installer_attribution_custom_label">اسم حزمة المثبِّت</string>
    <string name="installer_attribution_description">يمكن للتطبيقات معرفة المثبِّت الذي وضعها على جهازك. الافتراضي هو صدفة النظام.</string>
    <string name="installer_attribution_disclosure">تكشف بعض التطبيقات تغيُّر المثبِّت وقد ترفض العمل أو تفشل في فحوص الأمان (مثل Play Integrity وتطبيقات البنوك).</string>
    <string name="installer_attribution_preset_custom">مخصّص…</string>
    <string name="installer_attribution_preset_fdroid">F-Droid</string>
    <string name="installer_attribution_preset_obtainium">Obtainium</string>
    <string name="installer_attribution_preset_playstore">Play Store</string>
    <string name="installer_attribution_preset_system">افتراضي النظام</string>
    <string name="installer_attribution_title">إسناد المثبِّت</string>
    <string name="installer_type_dhizuku">Dhizuku</string>
    <string name="installer_type_dhizuku_description">تثبيت صامت عبر مالك الجهاز — يتجاوز نوافذ التثبيت الخاصة بالمصنّع</string>
    <string name="rate_limit_exceeded_retry_in">تم بلوغ حد الطلبات — أعد المحاولة بعد %1$d ث.</string>
    <string name="rate_limit_exceeded_signin_hint">سجّل الدخول إلى GitHub لحصة أعلى.</string>
    <string name="releases_unavailable_temporarily">الإصدارات غير متاحة مؤقتاً. يُرجى المحاولة بعد قليل.</string>
    <string name="starred_picker_already_tracked">متتبَّع</string>
    <string name="starred_picker_apk_badge">APK</string>
    <string name="starred_picker_empty">لا توجد مستودعات مميّزة بنجمة. ميّز مستودعات على GitHub لتظهر هنا.</string>
    <string name="starred_picker_filter_show_all">إظهار المستودعات بدون إصدارات APK</string>
    <string name="starred_picker_header_counts">%1$d مميّز · %2$d بإصدار APK · %3$d متتبَّع مسبقاً</string>
    <string name="starred_picker_no_match">لا توجد نتائج مطابقة.</string>
    <string name="starred_picker_progress">جارٍ الفحص %1$d / %2$d…</string>
    <string name="starred_picker_rate_limited">تم بلوغ حد طلبات GitHub. استأنف للمتابعة.</string>
    <string name="starred_picker_resume">استئناف</string>
    <string name="starred_picker_search_hint">ابحث في المالك / المستودع / الوصف</string>
    <string name="starred_picker_sign_in_required">سجّل الدخول إلى GitHub لرؤية مستودعاتك المميّزة بنجمة.</string>
    <string name="starred_picker_sort_alphabetical">أ → ي</string>
    <string name="starred_picker_sort_recent">المميّزة مؤخراً</string>
    <string name="starred_picker_sort_stars">الأكثر نجوماً</string>
    <string name="starred_picker_star_dedup_tooltip">إزالة النجمة من GitHub لن تُلغي تتبّع التطبيق.</string>
    <string name="import_stars_title">استيراد المستودعات المميّزة بنجمة باسم المستخدم</string>
    <string name="import_stars_subtitle">أدخل أي اسم مستخدم على GitHub لتصفّح مستودعاته العامة المميّزة بنجمة وإضافتها إلى المفضلة. لا حاجة لتسجيل الدخول.</string>
    <string name="import_stars_hint">اسم المستخدم على GitHub</string>
    <string name="import_stars_button">عرض المستودعات المميّزة بنجمة</string>
    <string name="import_stars_header_count">@%1$s · %2$d مستودع مميّز بنجمة</string>
    <string name="import_stars_search_hint">ابحث في المالك / المستودع / الوصف</string>
    <string name="import_stars_add_all">إضافة %1$d إلى المفضلة</string>
    <string name="import_stars_empty">‏@%1$s ليس لديه مستودعات مميّزة بنجمة.</string>
    <string name="import_stars_no_match">لا توجد نتائج مطابقة.</string>
    <string name="import_stars_add">إضافة إلى المفضلة</string>
    <string name="import_stars_added">موجود بالفعل في المفضلة</string>
    <string name="import_stars_try_another">جرّب اسماً آخر</string>
    <string name="import_stars_entry">استيراد المستودعات المميّزة بنجمة باسم المستخدم</string>
    <string name="starred_picker_title">إضافة من المميزة بنجمة</string>
    <string name="whats_new_cta_dismiss">فهمت</string>
    <string name="whats_new_cta_history">عرض الإصدارات السابقة</string>
    <string name="whats_new_history_empty">لا توجد إدخالات سجل تغييرات بعد.</string>
    <string name="whats_new_profile_description">أبرز ما في الإصدارات الأخيرة.</string>
    <string name="whats_new_section_fixed">إصلاحات</string>
    <string name="whats_new_section_heads_up">تنبيه</string>
    <string name="whats_new_section_improved">تحسينات</string>
    <string name="whats_new_section_new">جديد</string>
    <string name="whats_new_sheet_heading">ما الجديد في %1$s</string>
    <string name="whats_new_title">ما الجديد</string>
    <string name="whats_new_version_label">الإصدار %1$s · %2$s</string>

    <!-- Skip this version (issue #542) -->
    <string name="apps_skip_version">تخطّي هذا الإصدار</string>
    <string name="apps_skip_version_unskip">إلغاء التخطّي</string>
    <string name="apps_skip_version_snackbar">تم تخطّي %1$s — سيتم إعلامك عند صدور إصدار أحدث</string>
    <string name="apps_unskip_version_snackbar">تم تفعيل إشعار التحديث مجددًا</string>
    <string name="apps_skip_version_error">تعذّر تحديث التفضيل</string>
    <string name="apps_unskip_version_error">تعذّر استعادة إشعار التحديث</string>
    <string name="skipped_updates_entry_title">التحديثات المتخطّاة</string>
    <string name="skipped_updates_entry_description">الإصدارات التي اخترت تجاهلها</string>
    <string name="skipped_updates_title">التحديثات المتخطّاة</string>
    <string name="skipped_updates_empty_title">لا توجد إصدارات متخطّاة</string>
    <string name="skipped_updates_empty_description">عند تخطّي تحديث من شاشة التطبيقات، يظهر هنا حتى تتمكن من التراجع.</string>
    <string name="skipped_updates_skipped_label">تم تخطّي %1$s</string>
    <string name="skipped_updates_installed_label">المثبَّت: %1$s</string>
    <string name="skipped_updates_unskip_action">إلغاء التخطّي</string>
    <string name="skipped_updates_unskipped_snackbar">تم تفعيل الإشعار لـ %1$s</string>
    <string name="skipped_updates_unskip_failure">تعذّر تحديث التفضيل</string>
    <string name="hidden_repositories_title">المستودعات المخفية</string>
    <string name="hidden_repositories_entry_description">إدارة المستودعات التي أخفيتها من الرئيسية والبحث.</string>
    <string name="hidden_repositories_empty_title">لا توجد مستودعات مخفية</string>
    <string name="hidden_repositories_empty_description">اضغط مطولاً على بطاقة مستودع في الرئيسية أو البحث لإخفائه من الاستكشاف.</string>
    <string name="hidden_repositories_unhide_action">إظهار</string>
    <string name="hidden_repositories_unhide_all">إظهار الكل</string>
    <string name="hidden_repositories_unhidden_snackbar">تم إظهار %1$s</string>
    <string name="hidden_repositories_unhidden_all_snackbar">تم إظهار جميع المستودعات</string>
    <string name="hidden_repositories_unhide_failure">تعذر الإظهار. حاول مرة أخرى.</string>
    <string name="open_on_github">فتح في GitHub</string>
    <string name="mark_as_viewed">وضع علامة مشاهد</string>
    <string name="mark_as_unviewed">إلغاء علامة مشاهد</string>
    <string name="show_all_platforms_label">إظهار جميع المنصات</string>
    <string name="platform_section_android">Android</string>
    <string name="platform_section_windows">Windows</string>
    <string name="platform_section_macos">macOS</string>
    <string name="platform_section_linux">Linux</string>
    <string name="section_chip_your_device">جهازك</string>
    <string name="section_chip_for_transfer">للنقل</string>
    <string name="kao_banner_title">أبقِ أندرويد مفتوحًا</string>
    <string name="kao_banner_body">سياسة التحقق من المطورين من Google تهدد التوزيع المفتوح لأندرويد. Komi Store يدعم التحالف.</string>
    <string name="kao_banner_cta">اعرف المزيد</string>
    <string name="kao_banner_dismiss_cd">إغلاق البانر</string>

    <!-- Design refresh additions -->
    <string name="adaptive_pick_repo_subtitle">انقر على أي بطاقة على اليسار لعرض تفاصيلها هنا.</string>
    <string name="adaptive_pick_repo_title">اختر مستودعاً</string>
    <string name="apps_section_pending_installs">جاهز للتثبيت</string>
    <string name="apps_two_pane_advanced_settings">إعدادات متقدمة</string>
    <string name="apps_two_pane_detail_section_actions">إجراءات سريعة</string>
    <string name="apps_two_pane_detail_section_settings">الإعدادات</string>
    <string name="apps_two_pane_detail_section_status">الحالة</string>
    <string name="apps_two_pane_empty_subtitle">اختر أي تطبيق على اليسار لرؤية تفاصيله وإجراءاته.</string>
    <string name="apps_two_pane_empty_title">اختر تطبيقاً</string>
    <string name="apps_two_pane_installed_label">المثبَّت</string>
    <string name="apps_two_pane_latest_label">الأحدث</string>
    <string name="apps_two_pane_open_repo">فتح المستودع</string>
    <string name="apps_two_pane_pick_variant">اختيار النوع</string>
    <string name="apps_updates_banner_hide">إخفاء القائمة</string>
    <string name="apps_updates_banner_show">عرض القائمة</string>
    <string name="apps_updates_banner_subtitle">راجع أو حدّث كل شيء دفعة واحدة.</string>
    <string name="apps_updates_banner_title_one">تحديث واحد متاح</string>
    <string name="apps_updates_banner_title_other">%1$d تحديثات متاحة</string>
    <string name="back_cd">رجوع</string>
    <string name="cd_back">رجوع</string>
    <string name="cd_image">صورة</string>
    <string name="common_see_all">عرض الكل ›</string>
    <plurals name="custom_forges_count">
        <item quantity="zero">لا توجد مضيفات</item>
        <item quantity="one">مضيف واحد</item>
        <item quantity="two">مضيفان</item>
        <item quantity="few">%1$d مضيفات</item>
        <item quantity="many">%1$d مضيفاً</item>
        <item quantity="other">%1$d مضيف</item>
    </plurals>
    <string name="custom_forges_dialog_builtin_note">يتم البحث في Codeberg و gitea.com و git.disroot.org افتراضياً — لا حاجة لإضافتها هنا. استخدم هذه القائمة لمضيف Forgejo أو Gitea الذي تستضيفه بنفسك فقط.</string>
    <string name="details_about_screen_title">حول</string>
    <string name="details_developer_section">المطوّر</string>
    <string name="details_stats_section">الإحصائيات</string>
    <string name="details_view_developer_profile">عرض الملف الشخصي</string>
    <string name="details_whats_new_screen_title">ما الجديد</string>
    <string name="external_import_progress_skip">تخطّي والمراجعة لاحقاً</string>
    <string name="feedback_hub_subtitle">نقرأ كل تقرير.</string>
    <string name="home_action_get">الحصول</string>
    <string name="home_rank_format">#%1$d</string>
    <string name="home_section_from_your_stars">من مستودعاتك المميّزة</string>
    <string name="home_section_hot_releases">إصدارات رائجة</string>
    <string name="home_section_most_popular">الأكثر شعبية</string>
    <string name="home_section_trending_now">الأعلى تداولاً الآن</string>
    <string name="home_topbar_discover">استكشف</string>
    <string name="home_view_all">عرض الكل</string>
    <string name="home_view_more">عرض المزيد</string>
    <string name="host_tokens_action_add">إضافة رمز</string>
    <string name="host_tokens_action_back">رجوع</string>
    <string name="host_tokens_action_cancel">إلغاء</string>
    <string name="host_tokens_action_delete">حذف</string>
    <string name="host_tokens_action_save">حفظ</string>
    <string name="host_tokens_compose_add_title">إضافة رمز</string>
    <string name="host_tokens_compose_detected">تم الاكتشاف: %1$s</string>
    <string name="host_tokens_compose_field_forge_address">عنوان المنصّة</string>
    <string name="host_tokens_compose_replace_hint">اتركه فارغاً للاحتفاظ بالرمز الحالي. اكتب قيمة جديدة لاستبداله.</string>
    <string name="host_tokens_compose_replace_title">استبدال الرمز لـ %1$s</string>
    <string name="host_tokens_compose_will_connect">سيتم الاتصال بـ %1$s</string>
    <plurals name="host_tokens_count">
        <item quantity="zero">لا توجد رموز</item>
        <item quantity="one">رمز واحد</item>
        <item quantity="two">رمزان</item>
        <item quantity="few">%1$d رموز</item>
        <item quantity="many">%1$d رمزاً</item>
        <item quantity="other">%1$d رمز</item>
    </plurals>
    <string name="host_tokens_empty_subtitle">انقر على + لإضافة رمز وصول شخصي</string>
    <string name="host_tokens_empty_title">لا توجد رموز محفوظة</string>
    <string name="host_tokens_entry_subtitle">رموز الوصول الشخصية لكل مضيف منصّة (GitHub، Codeberg، Forgejo)</string>
    <string name="host_tokens_field_display_name">اسم العرض (اختياري)</string>
    <string name="host_tokens_field_token">رمز الوصول الشخصي</string>
    <string name="host_tokens_oauth_coexistence">أنت مسجَّل الدخول إلى GitHub عبر التطبيق — وهذا هو المسار الموصى به. أضف رمزاً هنا فقط إذا تعذّر تسجيل الدخول عبر المتصفح (شبكة مقيّدة، لا متصفح) أو لمنصّات غير GitHub.</string>
    <string name="host_tokens_picker_open_page">فتح صفحة الرمز</string>
    <string name="host_tokens_picker_other">منصّة أخرى</string>
    <string name="host_tokens_picker_other_subtitle">Forgejo، Gitea، استضافة ذاتية</string>
    <string name="host_tokens_picker_paste">لصق الرمز</string>
    <string name="host_tokens_picker_title">إضافة رمز لـ…</string>
    <string name="host_tokens_row_edit_label">تعديل التسمية</string>
    <string name="host_tokens_row_invalid_short">غير صالح · %1$s</string>
    <string name="host_tokens_row_menu">المزيد</string>
    <string name="host_tokens_row_open_token_page">الإدارة على %1$s</string>
    <string name="host_tokens_row_replace_token">استبدال الرمز</string>
    <string name="host_tokens_row_valid_rate">%1$s متبقٍ</string>
    <string name="host_tokens_row_valid_short">صالح · %1$s</string>
    <string name="host_tokens_row_validate">تحقّق</string>
    <string name="host_tokens_saved">تم حفظ الرمز لـ %1$s</string>
    <string name="host_tokens_title">رموز المصادقة</string>
    <string name="host_tokens_undo_action">تراجع</string>
    <string name="host_tokens_undo_failed">تعذّر استعادة الرمز لـ %1$s</string>
    <string name="host_tokens_undo_snackbar">تمت إزالة الرمز لـ %1$s</string>
    <string name="host_tokens_validation_failed">فشل التحقق: %1$s</string>
    <string name="host_tokens_validation_failed_fallback">خطأ غير معروف</string>
    <string name="host_tokens_validation_host_invalid">المضيف غير صالح</string>
    <string name="host_tokens_validation_host_required">المضيف مطلوب</string>
    <string name="host_tokens_validation_token_required">الرمز مطلوب</string>
    <string name="host_tokens_validation_token_short">الرمز قصير جداً</string>
    <string name="menubar_help_about">حول Komi Store</string>
    <string name="menubar_help_feedback">إرسال ملاحظات…</string>
    <string name="menubar_help_licenses">تراخيص المصادر المفتوحة</string>
    <string name="menubar_file_menu">ملف</string>
    <string name="menubar_go_menu">انتقال</string>
    <string name="menubar_file_quit">إنهاء</string>
    <string name="menubar_help_menu">مساعدة</string>
    <string name="menubar_help_privacy">سياسة الخصوصية</string>
    <string name="profile_tweaks_description">إعدادات التطبيق، السمة، الشبكة، الترجمة، الخيارات المتقدمة.</string>
    <string name="restart_banner_body">تتطلب بعض التغييرات إعادة تشغيل التطبيق لتفعيلها.</string>
    <string name="restart_banner_later">لاحقاً</string>
    <string name="restart_banner_reason_language">اللغة</string>    <string name="restart_banner_reason_theme">السمة</string>
    <string name="restart_banner_reasons_prefix">المتأثر: %1$s</string>
    <string name="restart_banner_restart_now">إعادة التشغيل الآن</string>
    <string name="search_clear_filter_cd">إزالة الفلتر</string>
    <string name="search_filters_apply">تم</string>
    <string name="search_filters_button">فلاتر</string>
    <string name="search_filters_reset">إعادة تعيين الكل</string>
    <string name="search_filters_section_language">اللغة</string>
    <string name="search_filters_section_platform">المنصّة</string>
    <string name="search_filters_section_sort">ترتيب حسب</string>
    <string name="search_filters_section_source">المصدر</string>
    <string name="search_filters_title">تصفية النتائج</string>
    <string name="section_app_block">التطبيق</string>
    <string name="section_connectivity">الاتصال</string>
    <string name="section_installs_and_updates">التثبيت والتحديثات</string>
    <string name="section_look_and_feel">المظهر</string>
    <string name="section_privacy_and_data">الخصوصية والبيانات</string>
    <plurals name="skipped_updates_count">
        <item quantity="zero">لا توجد تطبيقات</item>
        <item quantity="one">تطبيق واحد</item>
        <item quantity="two">تطبيقان</item>
        <item quantity="few">%1$d تطبيقات</item>
        <item quantity="many">%1$d تطبيقاً</item>
        <item quantity="other">%1$d تطبيق</item>
    </plurals>
    <string name="translation_auto_subtitle">ترجمة README وملاحظات الإصدار تلقائياً عند فتح مستودع. تستخدم لغة التطبيق كهدف.</string>
    <string name="translation_auto_target_followup">اتباع لغة التطبيق (%1$s)</string>
    <string name="translation_auto_target_label">الترجمة إلى</string>
    <string name="translation_auto_title">ترجمة المستودعات تلقائياً</string>
    <string name="translation_card_cancel">إلغاء</string>
    <string name="translation_card_change_language">تغيير اللغة</string>
    <string name="translation_card_detected_source">المصدر المكتشف: %1$s</string>
    <string name="translation_card_retry">إعادة المحاولة</string>
    <string name="translation_card_show_original">عرض النص الأصلي</string>
    <string name="translation_card_show_translation">عرض الترجمة</string>
    <string name="translation_card_subtitle_idle">اعرض هذه الصفحة بلغة أخرى.</string>
    <string name="translation_card_subtitle_original">عرض النص الأصلي</string>
    <string name="translation_card_subtitle_translated">تمت الترجمة إلى %1$s</string>
    <string name="translation_card_subtitle_translating">جارٍ الترجمة…</string>
    <string name="translation_card_target_label">اللغة الهدف</string>
    <string name="translation_card_title">ترجمة</string>
    <string name="translation_card_translate_to">الترجمة إلى %1$s</string>
    <string name="translation_deepl_auth_key">مفتاح المصادقة</string>
    <string name="translation_deepl_get_free_key">احصل على مفتاح DeepL مجاني ←</string>
    <string name="translation_deepl_help">سجّل في deepl.com/pro-api. مفاتيح الطبقة المجانية تنتهي بـ :fx وتستخدم نقطة النهاية المجانية تلقائياً. الطبقة المدفوعة تحافظ على خصوصية نصك؛ الطبقة المجانية قد تستخدم النص المرسَل لتحسين النماذج.</string>
    <string name="translation_deepl_save">حفظ المفتاح</string>
    <string name="translation_deepl_saved">تم حفظ مفتاح DeepL</string>
    <string name="translation_libre_api_key">مفتاح API (اختياري)</string>
    <string name="translation_libre_base_url">عنوان المثيل</string>
    <string name="translation_libre_help">يعمل مباشرةً عبر مرآة Disroot العامة — اترك الحقول فارغة لاستخدامها. لخصوصية أكبر، الصق رابط استضافتك الذاتية. لا يلزم مفتاح API إلا إذا اشترطه المثيل.</string>
    <string name="translation_libre_save">حفظ الإعدادات</string>
    <string name="translation_libre_saved">تم حفظ إعدادات LibreTranslate</string>
    <string name="translation_microsoft_get_free_key">احصل على مفتاح Azure مجاني ←</string>
    <string name="translation_microsoft_help">Azure Translator يحترم الخصوصية (وضع No-Trace افتراضياً — لا يُخزَّن نصك ولا يُستخدم للتدريب). الطبقة المجانية تغطي مليوني حرف شهرياً. المنطقة لازمة فقط للموارد غير العالمية.</string>
    <string name="translation_microsoft_key">مفتاح الاشتراك</string>
    <string name="translation_microsoft_region">المنطقة (مثل westeurope، اتركه فارغاً للعالمي)</string>
    <string name="translation_microsoft_save">حفظ بيانات الاعتماد</string>
    <string name="translation_microsoft_saved">تم حفظ بيانات اعتماد Microsoft Translator</string>
    <string name="translation_provider_deepl">DeepL</string>
    <string name="translation_provider_libre">LibreTranslate</string>
    <string name="translation_provider_microsoft">Microsoft</string>
    <string name="tweaks_app_info_app_name">Komi Store</string>
    <string name="tweaks_app_info_licenses_subtitle">المكتبات المستخدمة في التطبيق.</string>
    <string name="tweaks_app_info_licenses_title">تراخيص المصادر المفتوحة</string>
    <string name="tweaks_app_info_privacy_policy_subtitle">العرض على github-store.org.</string>
    <string name="tweaks_app_info_privacy_policy_title">سياسة الخصوصية</string>
    <string name="tweaks_app_info_source_code_subtitle">عرض كود هذا التطبيق.</string>
    <string name="tweaks_app_info_source_code_title">الكود المصدري على GitHub</string>
    <string name="tweaks_app_info_tagline">متجر تطبيقات عابر للمنصّات لإصدارات GitHub و Codeberg و Forgejo.</string>
    <string name="tweaks_app_info_whats_new_subtitle">ملاحظات الإصدارات السابقة.</string>
    <string name="tweaks_app_info_whats_new_title">ما الجديد</string>
    <string name="tweaks_connection_applies_to_all">يُطبَّق على كل الحركة ما لم يُعَد تجاوزه أدناه.</string>
    <string name="tweaks_connection_custom">مخصّص</string>
    <string name="tweaks_connection_intro_body">اختر وضع الاتصال أدناه. معظم المستخدمين يتركونه على 'بدون وكيل'.</string>
    <string name="tweaks_connection_intro_title">كيف يصل التطبيق إلى الإنترنت</string>
    <string name="tweaks_connection_main_section">الاتصال الرئيسي</string>
    <string name="tweaks_connection_mode_http">HTTP/HTTPS</string>
    <string name="tweaks_connection_mode_http_caption">معظم الوكلاء المؤسّسية.</string>
    <string name="tweaks_connection_mode_no_proxy">بدون وكيل</string>
    <string name="tweaks_connection_mode_socks">SOCKS5</string>
    <string name="tweaks_connection_mode_socks_caption">Tor، أنفاق SSH.</string>
    <string name="tweaks_connection_mode_system">النظام</string>
    <string name="tweaks_connection_overrides_body">يستخدم كل نطاق الاتصال الرئيسي افتراضياً. اختر 'مخصّص' للاحتفاظ بإعداداته الخاصة.</string>
    <string name="tweaks_connection_overrides_section">تجاوزات لكل نطاق</string>
    <string name="tweaks_connection_paste_url">لصق رابط كامل</string>
    <string name="tweaks_connection_paste_url_body">الصق رابط وكيل كاملاً وسنملأ النموذج نيابةً عنك.</string>
    <string name="tweaks_connection_paste_url_cta">استخدام هذا الرابط</string>
    <string name="tweaks_connection_paste_url_error">تعذّر قراءة هذا الرابط.</string>
    <string name="tweaks_connection_paste_url_placeholder">scheme://user:pass@host:port</string>
    <string name="tweaks_connection_paste_url_title">لصق رابط الوكيل</string>
    <string name="tweaks_connection_scope_discovery_body">واجهة GitHub البرمجية، البحث، تفاصيل المستودع.</string>
    <string name="tweaks_connection_scope_discovery_title">البحث والبيانات الوصفية</string>
    <string name="tweaks_connection_scope_download_body">تنزيلات APK والأصول.</string>
    <string name="tweaks_connection_scope_download_title">التنزيلات</string>
    <string name="tweaks_connection_scope_translation_body">مكالمات DeepL و Microsoft و LibreTranslate.</string>
    <string name="tweaks_connection_scope_translation_title">الترجمة</string>
    <string name="tweaks_connection_test">اختبار</string>
    <string name="tweaks_connection_use_main">استخدام الرئيسي</string>
    <string name="tweaks_entry_access_tokens">رموز الوصول</string>
    <string name="tweaks_entry_app_info">معلومات التطبيق</string>
    <string name="tweaks_entry_appearance">المظهر</string>
    <string name="tweaks_entry_connection">الاتصال</string>
    <string name="tweaks_entry_feedback">إرسال ملاحظات</string>
    <string name="tweaks_entry_install_method">طريقة التثبيت</string>
    <string name="tweaks_entry_language">اللغة</string>
    <string name="tweaks_entry_privacy">الخصوصية</string>
    <string name="tweaks_entry_sources">المصادر</string>
    <string name="tweaks_entry_storage">التخزين</string>
    <string name="tweaks_entry_subtitle_tap">انقر للإدارة</string>
    <string name="tweaks_entry_translation">الترجمة</string>
    <string name="tweaks_entry_updates">سلوك التحديث</string>
    <string name="tweaks_install_method_desktop_empty_body">المثبّتات الصامتة وإسناد المثبِّت ميزات خاصة بـ Android. عمليات التثبيت على سطح المكتب تمر عبر مدير حزم النظام.</string>
    <string name="tweaks_install_method_desktop_empty_title">طريقة التثبيت لـ Android فقط</string>
    <string name="tweaks_language_intro_body">يُعاد تشغيل التطبيق عند تبديل اللغة.</string>
    <string name="tweaks_licenses_intro_body">انقر على أي إدخال لفتح صفحة مشروعه.</string>
    <string name="tweaks_licenses_intro_title">يقوم Komi Store على هذه المكتبات.</string>
    <string name="tweaks_licenses_title">تراخيص المصادر المفتوحة</string>
    <string name="tweaks_privacy_browsing_history_section">سجل التصفّح</string>
    <string name="tweaks_privacy_clear_viewed_body">انسَ المستودعات التي فتحتها سابقاً.</string>
    <string name="tweaks_privacy_clear_viewed_dialog_body">لن يُلغي هذا تمييز أي مستودع بنجمة أو إضافته للمفضلة.</string>
    <string name="tweaks_privacy_clear_viewed_dialog_confirm">مسح</string>
    <string name="tweaks_privacy_clear_viewed_dialog_title">مسح سجل المشاهدة؟</string>
    <string name="tweaks_privacy_clear_viewed_title">مسح سجل المشاهدة</string>
    <string name="tweaks_privacy_clipboard_body">عند نسخك لرابط من github.com أو codeberg.org، سنطلب منك فتحه.</string>
    <string name="tweaks_privacy_clipboard_title">اكتشاف روابط المستودعات في الحافظة</string>
    <string name="tweaks_privacy_hidden_repos_body">المستودعات التي كتمتها من الموجَزات والبحث.</string>
    <string name="tweaks_privacy_hidden_repos_title">المستودعات المخفية</string>
    <string name="tweaks_privacy_hide_seen_body">تخطّي المستودعات المُشاهَدة في الموجَزات والبحث.</string>
    <string name="tweaks_privacy_hide_seen_title">إخفاء المستودعات التي شاهدتها بالفعل</string>    <string name="tweaks_privacy_telemetry_collect_no_identifiers">لا معرّفات.</string>    <string name="tweaks_privacy_telemetry_collect_os">نظام التشغيل والمنصّة.</string>    <string name="tweaks_search_empty">لا توجد إعدادات تطابق '%1$s'.</string>
    <string name="tweaks_search_placeholder">البحث في الإعدادات</string>
    <string name="tweaks_sources_add_a_host">إضافة مضيف Forgejo أو Gitea</string>
    <string name="tweaks_sources_added_hosts_section">المضيفات المضافة</string>
    <string name="tweaks_sources_github_mirror_title">مرآة GitHub</string>
    <string name="tweaks_sources_intro_body">يبحث التطبيق في GitHub افتراضياً. وجِّه عبر مرآة إقليمية أو أضف مضيفات Forgejo / Gitea مخصّصة.</string>
    <string name="tweaks_sources_intro_title">حيث يبحث التطبيق عن المستودعات</string>
    <string name="tweaks_sources_mirror_default">الافتراضي (github.com)</string>
    <string name="tweaks_storage_downloaded_apks_body">نحتفظ بالمثبّتات لتُستأنف التحديثات بسرعة.</string>
    <string name="tweaks_storage_downloaded_apks_clear">مسح</string>
    <string name="tweaks_storage_downloaded_apks_title">ملفات APK المنزَّلة</string>
    <string name="tweaks_storage_empty_size">0 ب</string>
    <string name="tweaks_storage_using_label">يستخدم: %1$s</string>
    <string name="tweaks_stub_coming_soon_body">هذه الشاشة جزء من التصميم الجديد قيد التطوير. الإعدادات لا تزال تعمل — يجري نقلها إلى هنا من التخطيط القديم.</string>
    <string name="tweaks_stub_coming_soon_title">قادم في تحديث لاحق</string>
    <plurals name="hidden_repositories_count">
        <item quantity="zero">لا مستودعات مخفية</item>
        <item quantity="one">مستودع مخفي واحد</item>
        <item quantity="two">مستودعان مخفيان</item>
        <item quantity="few">%1$d مستودعات مخفية</item>
        <item quantity="many">%1$d مستودعًا مخفيًا</item>
        <item quantity="other">%1$d مستودع مخفي</item>
    </plurals>
    <string name="tweaks_app_info_community_section">تواصل</string>
    <string name="tweaks_app_info_community_title">انضم إلى المجتمع</string>
    <string name="tweaks_app_info_community_subtitle">6 أماكن</string>
    <string name="tweaks_app_info_community_business_title">استفسارات الأعمال</string>
    <string name="tweaks_app_info_community_business_subtitle">الشراكات، الصحافة، التكاملات.</string>
    <string name="tweaks_app_info_community_business_cta">تواصل</string>
    <string name="profile_section_library">المكتبة</string>
    <string name="profile_section_updates">التحديثات</string>
    <string name="profile_section_account">الحساب</string>
    <string name="appearance_section_mode">الوضع</string>
    <string name="appearance_section_display">العرض</string>
    <string name="theme_dynamic">ديناميكي</string>
    <string name="auth_more_signin_options">خيارات تسجيل دخول إضافية</string>
    <string name="auth_hide_signin_options">إخفاء الخيارات</string>
    <string name="tweaks_sources_platforms_title">منصات الاكتشاف</string>
    <string name="tweaks_sources_platforms_body">تصفية الصفحة الرئيسية حسب المنصة. اترك الكل بدون تحديد لعرض كل شيء.</string>
    <string name="profile_entry_about_title">حول</string>
    <string name="profile_entry_about_subtitle">الإصدار، المجتمع، القانوني</string>
    <string name="filter_with_installable">قابل للتثبيت هنا</string>
    <string name="no_repos_with_installable">لا توجد مستودعات بأصول قابلة للتثبيت لهذه المنصة</string>
    <string name="interval_every_hours">كل %1$d ساعة</string>
    <string name="interval_daily">يوميًا</string>
    <string name="interval_every_days">كل %1$d أيام</string>
    <string name="interval_weekly">أسبوعيًا</string>
    <string name="interval_biweekly">كل أسبوعين</string>
    <string name="interval_monthly">كل 30 يومًا</string>

    <!-- Onboarding -->
    <string name="onboarding_palette_title">اختر لوحة ألوانك</string>
    <string name="onboarding_palette_subtitle">أربع لوحات ألوان × فاتح، داكن، AMOLED، النظام.</string>
    <string name="onboarding_signin_subtitle">نجومك وملفك الشخصي ومتّسع أكبر في حد الطلبات. اختياري — تخطَّ لتتصفّح كمجهول.</string>
    <string name="onboarding_signin_button">تسجيل الدخول</string>
    <string name="onboarding_permissions_title">طلبان سريعان</string>
    <string name="onboarding_permissions_subtitle">كلاهما اختياري. يمكنك تغييرهما لاحقاً من التعديلات.</string>
    <string name="onboarding_permission_notifications">الإشعارات</string>
    <string name="onboarding_permission_notifications_desc">تنبيهات التحديث وتقدّم التثبيت</string>
    <string name="onboarding_permission_install">تثبيت التطبيقات غير المعروفة</string>
    <string name="onboarding_permission_install_desc">مطلوب لتثبيت ملفات APK خارج Play</string>
    <string name="onboarding_permission_granted">ممنوح</string>
    <string name="onboarding_permission_allow">السماح</string>
    <string name="onboarding_skip">تخطّي</string>
    <string name="onboarding_get_started">لنبدأ</string>
    <string name="onboarding_next">التالي</string>

    <!-- Developer profile -->
    <string name="dev_profile_contribution_activity">نشاط المساهمات</string>
    <string name="dev_profile_contributions_this_year">%1$d هذا العام</string>
    <string name="dev_profile_contributions_load_failed">تعذّر تحميل المساهمات.</string>
    <string name="dev_profile_contributions_less">أقل</string>
    <string name="dev_profile_contributions_more">أكثر</string>
    <string name="dev_profile_org_badge">منظمة</string>

    <!-- Common -->
    <string name="loading">جارٍ التحميل…</string>
    <string name="failed_to_load">فشل التحميل</string>
    <string name="failed_to_load_details">فشل تحميل التفاصيل</string>

    <!-- Tweaks: licenses / app info / custom forges -->
    <string name="tweaks_licenses_load_failed">تعذّر تحميل التراخيص.</string>
    <string name="tweaks_app_info_website">الموقع الإلكتروني</string>
    <string name="tweaks_clear_downloads_failed">فشل مسح التنزيلات</string>
    <string name="tweaks_custom_forge_invalid_hostname">أدخل اسم مضيف صالحاً (مثل forgejo.example.com).</string>
    <string name="tweaks_custom_forge_save_failed">تعذّر حفظ المضيف. حاول مرة أخرى.</string>
    <string name="tweaks_custom_forge_remove_failed">تعذّر إزالة المضيف. حاول مرة أخرى.</string>

    <!-- Repo pages: issues -->
    <string name="repo_pages_issues_title">المشكلات</string>
    <string name="repo_pages_issues_filter_open">مفتوحة</string>
    <string name="repo_pages_issues_filter_closed">مغلقة</string>
    <string name="repo_pages_issues_empty_open">لا توجد مشكلات مفتوحة.</string>
    <string name="repo_pages_issues_empty_closed">لا توجد مشكلات مغلقة.</string>
    <string name="repo_pages_issue_comments_section">التعليقات</string>
    <string name="repo_pages_issue_no_body">لا يوجد وصف.</string>
    <string name="repo_pages_issue_opened_by">فتحها %1$s</string>

    <!-- Repo pages: security -->
    <string name="repo_pages_security_title">الأمان</string>
    <string name="repo_pages_security_advisories_header">التنبيهات الأمنية</string>
    <string name="repo_pages_security_no_advisories">لا توجد تنبيهات منشورة.</string>
    <string name="repo_pages_security_policy_header">سياسة الأمان</string>
    <string name="repo_pages_security_no_policy">لم تُنشر أي سياسة أمان.</string>
    <string name="repo_pages_severity_critical">حرج</string>
    <string name="repo_pages_severity_high">عالٍ</string>
    <string name="repo_pages_severity_medium">متوسط</string>
    <string name="repo_pages_severity_low">منخفض</string>
    <string name="repo_pages_severity_unknown">غير معروف</string>

    <!-- Repo pages: details entry -->
    <string name="repo_pages_details_issues_button">المشكلات</string>
    <string name="repo_pages_details_security_button">الأمان</string>

    <!-- Repo pages: details entry -->
    <string name="repo_pages_details_pulls_button">طلبات السحب</string>

    <!-- Repo interactions: star -->
    <string name="star_added">تم التمييز بنجمة</string>
    <string name="star_removed">تمت إزالة النجمة</string>
    <string name="star_sign_in_required">سجّل الدخول لتمييز المستودعات بنجمة.</string>

    <!-- Repo interactions: comments -->
    <string name="repo_pages_comment_hint">أضف تعليقاً…</string>
    <string name="repo_pages_comment_send">إرسال</string>
    <string name="repo_pages_comment_sign_in">سجّل الدخول للتعليق.</string>
    <string name="repo_pages_comment_failed">تعذّر نشر التعليق.</string>
    <string name="repo_pages_comment_posted">تم نشر التعليق</string>

    <!-- Repo interactions: new issue -->
    <string name="repo_pages_new_issue">مشكلة جديدة</string>
    <string name="repo_pages_new_issue_title_hint">العنوان</string>
    <string name="repo_pages_new_issue_body_hint">صِف المشكلة…</string>
    <string name="repo_pages_new_issue_submit">إنشاء</string>
    <string name="repo_pages_new_issue_sign_in">سجّل الدخول لفتح المشكلات.</string>
    <string name="repo_pages_new_issue_failed">تعذّر إنشاء المشكلة.</string>
    <string name="repo_pages_new_issue_created">تم إنشاء المشكلة</string>

    <!-- Repo interactions: reactions -->
    <string name="repo_pages_react_sign_in">سجّل الدخول للتفاعل.</string>
    <string name="repo_pages_react_failed">تعذّر إضافة التفاعل.</string>
    <string name="cd_thumbs_up">إعجاب</string>

    <!-- Repo pages: pull requests -->
    <string name="repo_pages_pulls_title">طلبات السحب</string>
    <string name="repo_pages_pulls_empty_open">لا توجد طلبات سحب مفتوحة.</string>
    <string name="repo_pages_pulls_empty_closed">لا توجد طلبات سحب مغلقة.</string>
    <string name="repo_pages_pr_state_merged">مُدمَج</string>
    <string name="repo_pages_pr_draft">مسودة</string>
</resources>
